Workbook

Sheet Totals
B1: Seen | C1: Own
A2: 1920 | B2: =IFERROR(SUM(INDIRECT(ADDRESS(2,2,,,$A2)&":"&ADDRESS(1000,2))),0) -> 0 | C2: =IFERROR(SUM(INDIRECT(ADDRESS(2,3,,,$A2)&":"&ADDRESS(1000,3))),0) -> 0
A3: 1921 | B3: =IFERROR(SUM(INDIRECT(ADDRESS(2,2,,,$A3)&":"&ADDRESS(1000,2))),0) -> 0 | C3: =IFERROR(SUM(INDIRECT(ADDRESS(2,3,,,$A3)&":"&ADDRESS(1000,3))),0) -> 0
A4: 1922 | B4: =IFERROR(SUM(INDIRECT(ADDRESS(2,2,,,$A4)&":"&ADDRESS(1000,2))),0) -> 0 | C4: =IFERROR(SUM(INDIRECT(ADDRESS(2,3,,,$A4)&":"&ADDRESS(1000,3))),0) -> 0
A5: 1923 | B5: =IFERROR(SUM(INDIRECT(ADDRESS(2,2,,,$A5)&":"&ADDRESS(1000,2))),0) -> 0 | C5: =IFERROR(SUM(INDIRECT(ADDRESS(2,3,,,$A5)&":"&ADDRESS(1000,3))),0) -> 0
A6: 1924 | B6: =IFERROR(SUM(INDIRECT(ADDRESS(2,2,,,$A6)&":"&ADDRESS(1000,2))),0) -> 0 | C6: =IFERROR(SUM(INDIRECT(ADDRESS(2,3,,,$A6)&":"&ADDRESS(1000,3))),0) -> 0
A7: 1925 | B7: =IFERROR(SUM(INDIRECT(ADDRESS(2,2,,,$A7)&":"&ADDRESS(1000,2))),0) -> 0 | C7: =IFERROR(SUM(INDIRECT(ADDRESS(2,3,,,$A7)&":"&ADDRESS(1000,3))),0) -> 0
A8: 1926 | B8: =IFERROR(SUM(INDIRECT(ADDRESS(2,2,,,$A8)&":"&ADDRESS(1000,2))),0) -> 0 | C8: =IFERROR(SUM(INDIRECT(ADDRESS(2,3,,,$A8)&":"&ADDRESS(1000,3))),0) -> 0
A9: 1927 | B9: =IFERROR(SUM(INDIRECT(ADDRESS(2,2,,,$A9)&":"&ADDRESS(1000,2))),0) -> 0 | C9: =IFERROR(SUM(INDIRECT(ADDRESS(2,3,,,$A9)&":"&ADDRESS(1000,3))),0) -> 0
A10: 1928 | B10: =IFERROR(SUM(INDIRECT(ADDRESS(2,2,,,$A10)&":"&ADDRESS(1000,2))),0) -> 0 | C10: =IFERROR(SUM(INDIRECT(ADDRESS(2,3,,,$A10)&":"&ADDRESS(1000,3))),0) -> 0
A11: 1929 | B11: =IFERROR(SUM(INDIRECT(ADDRESS(2,2,,,$A11)&":"&ADDRESS(1000,2))),0) -> 0 | C11: =IFERROR(SUM(INDIRECT(ADDRESS(2,3,,,$A11)&":"&ADDRESS(1000,3))),0) -> 0
A12: 1930 | B12: =IFERROR(SUM(INDIRECT(ADDRESS(2,2,,,$A12)&":"&ADDRESS(1000,2))),0) -> 0 | C12: =IFERROR(SUM(INDIRECT(ADDRESS(2,3,,,$A12)&":"&ADDRESS(1000,3))),0) -> 0
A13: 1931 | B13: =IFERROR(SUM(INDIRECT(ADDRESS(2,2,,,$A13)&":"&ADDRESS(1000,2))),0) -> 0 | C13: =IFERROR(SUM(INDIRECT(ADDRESS(2,3,,,$A13)&":"&ADDRESS(1000,3))),0) -> 0
... A114: 2032 | B114: =IFERROR(SUM(INDIRECT(ADDRESS(2,2,,,$A114)&":"&ADDRESS(1000,2))),0) -> 0 | C114: =IFERROR(SUM(INDIRECT(ADDRESS(2,3,,,$A114)&":"&ADDRESS(1000,3))),0) -> 0

Sheet 2026
B1: Seen | C1: Own | D1: Want to see | E1: Where | F1: IMDb | G1: =SUM(B:B) -> 23 | H1: =_xlfn.CONCAT(SUM(C:C)," (",SUMPRODUCT(C:C,--(NOT(B:B=1))),")") -> 29 (21) | I1: 46192
A2: The Rip | D2: 1 | E2: Netflix | G2: en
A3: Joe's College Road Trip | E3: Netflix | G3: en
A4: War Machine | D4: 1 | E4: Netflix | G4: en
A5: Peaky Blinders: The Immortal Man | E5: Netflix | G5: en
A6: In the Blink of an Eye | E6: Hulu | G6: en
A7: The Wrecking Crew | D7: 1 | E7: Prime | G7: en
A8: Relationship Goals | E8: Prime | G8: en
A9: Love Me Love Me | E9: Prime | G9: en
A10: The Bluff | E10: Prime | G10: en
A11: The Mother and the Bear
A12: We Bury the Dead
A13: Greenland 2: Migration | B13: 1
A14: Primate | C14: 1 | D14: 1
A15: Dead Man's Wire
A16: I Was A Stranger
A17: Magellan | D17: 1
A18: My Neighbor Adolf
A19: OBEX
A20: People We Meet on Vacation | D20: 1
A21: Young Mothers
A22: 28 Years Later: The Bone Temple
A23: Charlie the Wonderdog
A24: All You Need Is Kill
A25: A Private Life
A26: Killer Whale
A27: Night Patrol
A28: Sound of Falling
A29: A Useful Ghost
A30: Clika
A31: H is for Hawk | D31: 1
A32: Mercy
A33: Return to Silent Hill
A34: In Cold Light
A35: Mel Brooks: The 99 Year Old Man! | D35: 1
A36: Hard Boiled
A37: Iron Lung
A38: Send Help | B38: 1
A39: Shelter | C39: 1 | D39: 1
A40: Worldbreaker
A41: Islands
A42: The Love That Remains
A43: The Moment
A44: A Poet
A45: Dracula | D45: 1
A46: Solo Mio | D46: 1
A47: The Strangers: Chapter 3
A48: Whistle
A49: Buffalo Kids
A50: Calle Málaga
A51: Jimpa
A52: Kokuho
A53: Pillion | C53: 1 | D53: 1
A54: The President's Cake
A55: Scarlet
A56: Twisted
A57: Cold Storage | C57: 1 | D57: 1 | E57: Plex
A58: Crime 101 | C58: 1 | D58: 1
A59: GOAT | D59: 1
A60: Good Luck, Have Fun, Don't Die | C60: 1 | D60: 1 | E60: Plex
A61: Wuthering Heights | B61: 1 | C61: 1 | E61: Plex
A62: Mimics
A63: The Mortuary Assistant
A64: My Father's Shadow
A65: Nirvanna the Band the Show the Movie | D65: 1
A66: How to Make a Killing | D66: 1
A67: I Can Only Imagine 2
A68: Psycho Killer
A69: Blades of the Guardians
A70: The Dreadful
A71: EPiC: Elvis Presley in Concert
A72: Midwinter Break
A73: Redux Redux | C73: 1 | D73: 1 | E73: Plex
A74: This Is Not a Test
A75: K-Pops!
A76: Scream 7
A77: Dreams | D77: 1
A78: The Drift
A79: For Worse | D79: 1
A80: Ghost Elephants
A81: Idiotka
A82: Man on the Run
A83: Matter of Time
A84: The Napa Boys
A85: Operation Taco Gary's | D85: 1
A86: Space Cowboy
A87: Starbright
A88: Undercard | D88: 1
A89: A Better Tomorrow
A90: The Bride! | B90: 1 | C90: 1 | D90: 1 | E90: Plex
A91: Hoppers | B91: 1 | C91: 1 | E91: Plex
A92: Protector
A93: André is an Idiot
A94: Dolly
A95: Heel
A96: Mother's Baby
A97: Pompei: Below the Clouds
A98: Youngblood
A99: The Optimist
A100: Reminders of Him
...

Sheet 2025
B1: Seen | C1: Own | D1: Want to see | E1: Where | F1: IMDb | G1: =SUM(B:B) -> 78 | H1: =_xlfn.CONCAT(SUM(C:C)," (",SUMPRODUCT(C:C,--(NOT(B:B=1))),")") -> 66 (25) | I1: 46387
A2: No Other Choice | D2: 10 | E2: 19.99 | F2: 7.6 | G2: ko | H2: After being laid off and humiliated by a ruthless job market, a veteran paper mill manager descends into violence in a desperate bid to reclaim his dignity.
A3: Sentimental Value | C3: 1 | D3: 9 | E3: Plex | F3: 7.9 | G3: no | H3: An intimate exploration of family, memories, and the reconciliatory power of art.
A4: Twinless | C4: 1 | D4: 8 | E4: Plex | F4: 7.5 | G4: en | H4: A young man grieving the loss of his twin brother joins a support group for "twinless twins."
A5: The Smashing Machine | C5: 1 | D5: 8 | E5: Hulu | F5: 6.7 | G5: en | H5: The true story of mixed martial arts and UFC fighter Mark Kerr, whose obsession with greatness made him a legend -- and nearly cost him everything.
A6: Together | C6: 1 | D6: 8 | E6: Plex | F6: 6.7 | G6: en | H6: With a move to the countryside already testing the limits of a couple's relationship, a supernatural encounter begins an extreme transformation of their love, their lives, and their flesh.
A7: Blue Moon | D7: 8 | E7: 20.95 | F7: 7.3 | G7: en | H7: On the evening of March 31, 1943, legendary lyricist Lorenz Hart confronts his shattered self-confidence in Sardi’s bar as his former collaborator Richard Rodgers celebrates the opening night of his ground-breaking hit musical “Oklahoma!”.
A8: Ballad of a Small Player | D8: 8 | E8: Netflix | F8: 5.8 | G8: en | H8: Amid the glittering casinos of Macau, a gambler running from his past — and his debts — becomes fascinated by an enigmatic woman at the baccarat table.
A9: I'm Still Here | C9: 1 | D9: 7 | E9: Plex | F9: 8.1 | G9: pt | H9: A woman married to a former politician during the 1971 military dictatorship in Brazil is forced to reinvent herself and chart a new course for her family after a violent and arbitrary act.
A10: Song Sung Blue | C10: 1 | D10: 7 | E10: Plex | F10: 7.5 | G10: en | H10: After meeting at a gig for musical impersonators, Mike and Claire decide to form a Neil Diamond tribute act. They grow closer through their rehearsals, and despite their separate years of hurt and disappointments, they fall in love and begin touring together. The couple form the band “Thunder & Lightning” and take their infectious energy across the country.
A11: If I Had Legs I'd Kick You | C11: 1 | D11: 7 | E11: Plex | F11: 7.3 | G11: en | H11: With her life crashing down around her, Linda attempts to navigate her child's mysterious illness, her absent husband, a missing person, and an increasingly hostile relationship with her therapist.
A12: Bring Her Back | C12: 1 | D12: 7 | E12: Plex | F12: 7.2 | G12: en | H12: Following the death of their father, a brother and sister are sent to live with a foster mother, only to learn that she is hiding a terrifying secret.
A13: Eden | C13: 1 | D13: 7 | E13: Plex | F13: 6.5 | G13: en | H13: A group of disillusioned outsiders abandon modern society in search of a new beginning. Settling on a remote, uninhabited island, their utopian dream quickly unravels as they discover that the greatest threat isn’t the brutal climate or deadly wildlife, but each other.
A14: Good Boy | C14: 1 | D14: 7 | F14: 6.2 | G14: en | H14: A loyal dog moves to a rural family home with his owner Todd, only to discover supernatural forces lurking in the shadows. As dark entities threaten his human companion, the brave pup must fight to protect the one he loves most.
A15: Truth & Treason | C15: 1 | D15: 7 | E15: Plex | G15: en
A16: Don't Let's Go to the Dogs Tonight | D16: 7 | E16: Netflix | F16: 6.9 | G16: en | H16: Depicts 8-year-old Bobo's life on her family's Rhodesian farm during the Bush War's final stages. It explores the family's bond with Africa's land and the war's impact on the region and individuals through Bobo's perspective.
A17: Arco | D17: 7
A18: Relay | C18: 1 | D18: 6 | E18: Plex | F18: 7 | G18: en | H18: A broker of lucrative payoffs between corrupt corporations and the individuals who threaten them breaks his own rules when a new client seeks his protection to stay alive.
A19: Materialists | C19: 1 | D19: 6 | E19: Plex | F19: 6.3 | G19: en | H19: An ambitious young New York City matchmaker finds herself torn between the perfect match and her imperfect ex.
A20: Drop | C20: 1 | D20: 6 | E20: Plex | F20: 6.1 | G20: en | H20: A widowed mother's first date in years takes a terrifying turn when she's bombarded with anonymous threatening messages on her phone during their upscale dinner, leaving her questioning if her charming date is behind the harassment.
A21: The Wilderness | D21: 6 | E21: 7.99 | F21: 8.2 | G21: en | H21: Kidnapped and abandoned in the Utah desert, a group of troubled boys are forced into a ruthless "Wilderness Therapy" program. Cut off from the world, they must survive both the elements and the mind games of a director who may not be trying to save them at all.
A22: Clemente | D22: 6 | E22: 12.99 | F22: 8.2 | G22: en | H22: An immersive documentary about the remarkable life and legacy of MLB icon Roberto Clemente.
A23: The History of Sound | D23: 6 | E23: 21.69 | F23: 6.9 | G23: en | H23: In 1917, two young music students attending the Boston Conservatory bond over their mutual love of folk music. They reconnect a few years later, embarking on a song collecting trip in the backwaters of Maine.
A24: Die My Love | D24: 6 | E24: 26.99 | F24: 6.5 | G24: en | H24: Grace, a writer and young mother, is slowly slipping into madness. Locked away in an old house in Montana, her increasingly agitated and erratic behaviour leaves her companion, Jackson, worried and helpless.
A25: Black Phone 2 | C25: 1 | D25: 5 | E25: Plex | F25: 6.6 | G25: en | H25: Four years after escaping The Grabber, Finney Blake is struggling with his life after captivity. When his sister Gwen begins receiving calls in her dreams from the black phone and seeing disturbing visions of three boys being stalked at a winter camp, the siblings become determined to solve the mystery and confront a killer who has grown more powerful in death and more significant to them than either could imagine.
A26: Dust Bunny | C26: 1 | D26: 5 | E26: Plex
A27: John Candy: I Like Me | D27: 5 | E27: Prime | F27: 8.1 | G27: en | H27: From director Colin Hanks and producer Ryan Reynolds--both lifelong John Candy fans--comes John Candy: I Like Me, an exploration of the life and legacy of the comedic icon. The film showcases Candy's remarkable career, from his breakout turn on SCTV in his beloved native Canada to starring in some of the biggest comedies of all time. But it also delves deeply into Candy's life off-camera, through never-before-seen home videos and the personal recollections of those who knew him best. A remarkable roster of family members, close friends and colleagues share their memories of John Candy, creating an intimate and indelible portrait of an unforgettable talent who helped define a cinematic era. John Candy: I Like Me tells the story of a son, husband, father, friend, and star, driven to bring joy to audiences and loved ones while battling personal ghosts and Hollywood pressures.
A28: Re-Election | D28: 5 | E28: 7.99 | F28: 7.9 | G28: en | H28: A wry, warm, and witty coming of (middle) age comedy, RE-ELECTION follows a 40-something underdog who returns to high school to reboot his past and finally win the race for class president.
A29: Little Amélie or the Character of Rain | D29: 5 | E29: 22.99 | F29: 7.6 | G29: fr | H29: The world is a perplexing, peaceful mystery to Amélie until a miraculous encounter with chocolate ignites her wild sense of curiosity. As she develops a deep attachment to her family's housekeeper, Nishio-san, Amélie discovers the wonders of nature as well as the emotional truths hidden beneath the surface of her family's idyllic life as foreigners in post-war Japan.
A30: Secret Mall Apartment | D30: 5 | E30: Paramount | F30: 7.2 | G30: en | H30: A struggling young dancer finds herself drawn in by dark forces when a peculiar, well-connected older couple promise her a shot at fame.
A31: The Perfect Neighbor | D31: 5 | E31: Netflix | F31: 7.1 | G31: en | H31: Police bodycam footage reveals how a long-running neighborhood dispute turned fatal in this documentary about fear, prejudice and Stand Your Ground laws.
A32: Lurker | D32: 5 | E32: 25.89 | F32: 6.9 | G32: en | H32: When a twenty-something retail clerk meets a rising popstar, he takes the opportunity to edge his way into the in-crowd. But as the line between friend and fan blurs beyond recognition, access and proximity become a matter of life and death.
A33: Waltzing with Brando | D33: 5 | E33: 14.99 | F33: 6.7 | G33: en | H33: The story of how Marlon Brando plucked Bernard Judge, an obscure but idealistic Los Angeles architect from his stable existence and convinced him that he should build the world’s first ecologically perfect retreat on a tiny and uninhabitable Tahitian island.
A34: Christy | D34: 5 | E34: 19.98 | F34: 6.2 | G34: en | H34: Christy Martin never imagined life beyond her small-town roots in West Virginia—until she discovered a knack for punching people. Fueled by grit, raw determination, and an unshakable desire to win, she charges into the world of boxing under the guidance of her trainer and manager-turned-husband, Jim. But while Christy flaunts a fiery persona in the ring, her toughest battles unfold outside it—confronting family, identity, and a relationship that just might become life-or-death.
A35: The Luckiest Man in America | D35: 5 | E35: Hulu | F35: 6.2 | G35: en | H35: May 1984. An unemployed ice cream truck driver steps onto the game show Press Your Luck harboring a secret: the key to endless money. But his winning streak is threatened when the bewildered executives uncover his real motivations.
A36: Regretting You | D36: 5 | E36: Paramount | F36: 6.2 | G36: en | H36: Morgan Grant and her daughter Clara explore what's left behind after a devastating accident reveals a shocking betrayal and forces them to confront family secrets, redefine love, and rediscover each other.
A37: Bring Them Down | C37: 1 | D37: 4 | E37: Plex | F37: 6.4 | G37: en | H37: When the ongoing rivalry between farmers Michael and Jack suddenly escalates, it triggers a chain of events that take increasingly violent and devastating turns, leaving both families permanently altered.
A38: The Ballad of Wallis Island | D38: 4 | E38: Prime | F38: 7.4 | G38: en | H38: An eccentric lottery winner who lives alone on a remote island tries to make his fantasies come true by getting his favourite musicians to perform at his home.
A39: Extremely Unique Dynamic | D39: 4 | E39: 12.99 | F39: 7.2 | G39: en | H39: Ryan and Daniel, two childhood best friends and aspiring actors, spend one final weekend together before RYAN has to move to Canada with his fiancé. Wanting to create one lasting memory, they decide to make a movie... about two guys making a movie.. about two guys making a movie. Along the way, they unpack their decades-long friendship and prepare for the next chapters of their respective lives.
A40: Splitsville | D40: 4 | E40: 9.99 | F40: 6.5 | G40: en | H40: After Ashley asks for a divorce, good-natured Carey runs to his friends, Julie and Paul, for support. He’s shocked to discover that the secret to their happiness is an open marriage, that is until Carey crosses the line and throws all of their relationships into chaos.
A41: Happy Gilmore 2 | D41: 4 | E41: Netflix | F41: 6.1 | G41: en | H41: Happy Gilmore isn't done with golf — not by a long shot. Since his retirement after his first Tour Championship win, Gilmore returns to finance his daughter's ballet classes.
A42: The SpongeBob Movie: Search for SquarePants | D42: 4 | E42: 24.99 | F42: 5.8 | G42: en | H42: SpongeBob travels to the deepest darkest parts of the ocean on a new quest. He must face the ghost of the Flying Dutchman. This perilous mission sees SpongeBob and his friends Squidward, Sandy, and Mr. Krabs on a mission they will never forget.
A43: Anemone | D43: 4 | E43: Peacock | F43: 5.7 | G43: en | H43: Middle-aged Jem sets out from his suburban home on a journey into the woods, where he reconnects with his estranged hermit brother Ray. Bonded by a mysterious, complicated past, the men share a fraught, if occasionally tender relationship—one that was forever altered by shattering events decades earlier.
A44: Bunny | D44: 4 | E44: 14.99
A45: Anniversary | C45: 1 | D45: 3 | E45: Plex | F45: 7 | G45: en | H45: When Ellen and Paul’s son introduces his new girlfriend one lovely afternoon at their 25th anniversary party, no one suspects that it is the beginning of the end for this happy family. The new girlfriend is Liz, Ellen’s former student, who left the university, some years before, after Ellen called her out in class for her radical ideology.
A46: Opus | C46: 1 | D46: 3 | E46: Max | F46: 5.7 | G46: en | H46: A young writer is invited to the remote compound of a legendary pop star who mysteriously disappeared thirty years ago. Surrounded by the star's cult of sycophants and intoxicated journalists, she finds herself in the middle of his twisted plan.
A47: Adulthood | C47: 1 | D47: 3 | E47: Plex | F47: 5.5 | G47: en | H47: The lives of two siblings are completely upended when they discover a dead body, long buried in their parent’s basement, sending them down a rabbit hole of crime and murder.
A48: No Other Land | D48: 3 | E48: 7.99 | F48: 8.3 | G48: ar | H48: This film made by a Palestinian-Israeli collective shows the destruction of the occupied West Bank's Masafer Yatta by Israeli soldiers and the alliance which develops between the Palestinian activist Basel and Israeli journalist Yuval.
A49: Are We Good? | D49: 3 | E49: 9.99 | F49: 7.7 | G49: en | H49: Comic and podcast pioneer Marc Maron reflects on loss and growth after the death of his partner, Lynn Shelton. As he processes grief and crafts comedy, he revisits his career, family struggles, and the evolving comedy world at 60.
A50: The White House Effect | D50: 3 | E50: Netflix | F50: 7.3 | G50: en | H50: Exploring the dramatic origin story of the climate crisis and how a political battle in the George H.W. Bush administration changed the course of history.
A51: Thank You Very Much | D51: 3 | E51: Plex | F51: 7.3 | G51: en | H51: Andy Kaufman's provocative comedy often outraged audiences, challenging them to confront their own presumptions. Through never-before-seen footage and intimate recollections, filmmaker Alex Braverman explores Kaufman’s brief but impactful life and career. As the lines between performance and reality blur in our present age, Kaufman’s genius resonates more than ever.
A52: The Penguin Lessons | D52: 3 | E52: Hulu | F52: 7.1 | G52: en | H52: Inspired by a true story; an enchanting adventure about a lost penguin rescued from an oil spill, who transforms the life of a heartbroken fisherman. They soon become unlikely friends, so bonded that even the vast ocean cannot divide them.
A53: On Becoming a Guinea Fowl | D53: 3 | E53: Max | F53: 7 | G53: en | H53: On an empty road in the middle of the night, Shula stumbles across the body of her uncle. As funeral proceedings begin around them, she and her cousins bring to light the buried secrets of their middle-class Zambian family.
A54: The Testament of Ann Lee | D54: 3 | F54: 7 | G54: en | H54: Ann Lee was a revered leader of a fledgling sect that would come to be known as the Shakers. At the heart of her teachings was a radical social equality, but it was infused with an ecstatic religious practice that turned her followers into devotees. A spiritual leader in the truest sense, Ann Lee rose beyond a figurehead and into a persecuted, Christ-like master who inspired unwavering loyalty.
A55: The Senior | D55: 3 | E55: 14.99 | F55: 6.6 | G55: en | H55: Nearly four decades after being kicked off his team, Mike returns to his alma mater to take the hit that changed everything. Bruised, doubted, and nearly broken, he fights for one last shot at the ending he still believes is possible.
A56: The Ruse | C56: 1 | D56: 2 | E56: Plex | F56: 6.9 | G56: en | H56: An in-home caregiver fears for her life after being assigned to a mysterious elderly patient in a remote seaside home.
A57: Neighborhood Watch | C57: 1 | D57: 2 | E57: Plex | F57: 6.2 | G57: en | H57: When a mentally ill young man thinks he witnesses an abduction and the police refuse to believe him, he reluctantly turns to his next-door neighbor, a bitter and retired security guard, to help him find the missing person.
A58: Heart Eyes | C58: 1 | D58: 2 | E58: Netflix | F58: 6 | G58: en | H58: When the "Heart Eyes Killer" strikes Seattle, a pair of co-workers pulling overtime on Valentine's Day are mistaken for a couple by the elusive couple-hunting killer. Now, they must spend the most romantic night of the year running for their lives.
A59: The Alto Knights | C59: 1 | D59: 2 | E59: Plex | F59: 5.9 | G59: en | H59: When a headstrong street orphan, Seiya, in search of his abducted sister unwittingly taps into hidden powers, he discovers he might be the only person alive who can protect a reincarnated goddess, sent to watch over humanity. Can he let his past go and embrace his destiny to become a Knight of the Zodiac?
A60: Predator: Killer of Killers | D60: 2 | E60: Hulu | F60: 7.5 | G60: en | H60: The anthology story follows three of the fiercest warriors in human history: a Viking raider guiding her young son on a bloody quest for revenge, a ninja in feudal Japan who turns against his Samurai brother in a brutal battle for succession, and a WWII pilot who takes to the sky to investigate an otherworldly threat to the Allied cause. But while all these warriors are killers in their own right, they are merely prey for their new opponent -- the ultimate killer of killers.
A61: Lost in Starlight | D61: 2 | E61: Netflix | F61: 7.1 | G61: ko | H61: When an astronaut leaves Earth for Mars, the vast infinite space divides star-crossed lovers in this animated romance that crosses the cosmos.
A62: Universal Language | D62: 2 | E62: 5 | F62: 6.9 | G62: fa | H62: An absurdist triptych of seemingly unconnected stories finds a mysterious point of intersection in this tale set somewhere between Winnipeg and Tehran.
A63: The Roses | D63: 2 | E63: Hulu | F63: 6.8 | G63: en | H63: Life seems easy for picture-perfect couple Ivy and Theo: successful careers, a loving marriage, great kids. But beneath the façade of their supposed ideal life, a storm is brewing – as Theo's career nosedives while Ivy's own ambitions take off, a tinderbox of fierce competition and hidden resentment ignites.
A64: Nonnas | D64: 2 | E64: Netflix | F64: 6.8 | G64: en | H64: After losing his beloved mother, a man risks everything to honor her by opening an Italian restaurant with actual nonnas — grandmothers — as the chefs.
A65: The Gorge | D65: 2 | E65: Apple | F65: 6.7 | G65: en | H65: Two highly trained operatives grow close from a distance after being sent to guard opposite sides of a mysterious gorge. When an evil below emerges, they must work together to survive what lies within.
A66: Zodiac Killer Project | D66: 2 | E66: 12.99 | F66: 6.6 | G66: en | H66: Against the backdrop of deserted spaces, a filmmaker explores his abandoned Zodiac Killer documentary, delving into the true crime genre's inner workings at a saturation point.
A67: Eleanor the Great | D67: 2 | E67: Netflix | F67: 6.6 | G67: en | H67: 94-year-old Eleanor Morgenstein tries to rebuild her life after the death of her best friend. As a result, she moves back to New York City after living in Florida for decades.
A68: Grand Tour | D68: 2 | E68: 14.99 | F68: 6.5 | G68: pt | H68: In 1917 Burma (now Myanmar), a British diplomat is set to marry his fiancée, but after a sudden panic, escapes to Singapore, sending her on what evolves into a chase across Asia.
A69: Freakier Friday | D69: 2 | E69: Disney | F69: 6.5 | G69: en | H69: 22 years after Tess and Anna endured an identity crisis, Anna now has a daughter and a soon-to-be stepdaughter. As they navigate the challenges that come when two families merge, Tess and Anna discover that lightning might strike twice.
A70: One of Them Days | D70: 2 | E70: Peacock | F70: 6.5 | G70: en | H70: The Mad Hatter has hunted down princesses from the fairytale lands; Ariel, Belle, Alice, Cinderella, Snow White, Tinkerbell and Sleeping Beauty and makes them fight in a Hunger Games style death match. Who is the fairest of them all?
A71: My Dead Friend Zoe | D71: 2 | E71: Prime | F71: 6.5 | G71: en | H71: A group of college friends rent an Airbnb for the biggest music festival of the year. A weekend of partying quickly takes a turn, as the group is murdered one by one.
A72: The Choral | D72: 2 | F72: 6.5 | G72: en | H72: During World War I, in Yorkshire, England, a local choir loses all its male members to the war effort. The new leader of the choir, Dr. Guthrie, comes under suspicion for having worked in Germany, but his talent cannot be questioned. He raises a choir of young teenagers who are all on the verge of conscription but come together to experience the joy of singing in unison.
A73: The Threesome | D73: 2 | E73: Netflix | F73: 6.1 | G73: en | H73: Connor and his long-time crush Olivia engage in a threesome with a sweet, alluring stranger named Jenny. This encounter sparks a relationship between Connor and Olivia, leading them to plan a life together. However, their romance faces challenges when Jenny reappears, thrusting all three into a difficult journey toward true accountability and adulthood.
A74: A Minecraft Movie | D74: 2 | E74: Max | F74: 5.6 | G74: en | H74: Four misfits are suddenly pulled through a mysterious portal into a bizarre cubic wonderland that thrives on imagination. To get back home they'll have to master this world while embarking on a quest with an unexpected expert crafter.
A75: Ella McCay | D75: 2 | E75: 19.99 | F75: 5.1 | G75: en | H75: When Ella McCay becomes the governor of her home state, she has a lot to juggle. Her family is thrown into chaos by her appointment as their lives are turned upside down. As Ella seizes the opportunity to make a real difference in people’s lives across the state, she has to survive the onslaught of interpersonal drama that comes with being both idealistic and compassionate.
A76: The Old Guard 2 | D76: 2 | E76: Netflix | F76: 5.1 | G76: en | H76: Andy leads immortal warriors against a powerful enemy threatening their group. They grapple with the resurfacing of a long-lost immortal, complicating their mission to safeguard humanity.
A77: Him | D77: 2 | E77: Peacock | F77: 5.1 | G77: en | H77: After suffering a potentially career-ending brain trauma, Cameron Cade receives a lifeline when his hero, legendary eight-time Championship quarterback and cultural megastar Isaiah White, offers to train Cam at Isaiah's isolated compound that he shares with his celebrity influencer wife. But as Cam's training accelerates, Isaiah's charisma begins to curdle into something darker.
A78: The Unbreakable Boy | C78: 1 | D78: 1 | E78: Plex | F78: 6 | G78: en | H78: A young boy with both a rare brittle-bone disease and autism transforms everyone around him with his joyous, funny, and life-affirming world view.
A79: It Was Just An Accident | D79: 1 | F79: 7.7 | G79: fa | H79: Vahid, an Azerbaijani auto mechanic, was once imprisoned by Iranian authorities. During his sentence, he was interrogated blindfolded. One day, a man named Eghbal enters his workshop. His prosthetic leg creaks, and Vahid thinks he recognizes one of his former torturers.
A80: Sly Lives! | D80: 1 | E80: Max | F80: 7.6 | G80: en | H80: After decades apart, childhood friends Nora and Hae Sung are reunited in New York for one fateful weekend as they confront notions of destiny, love, and the choices that make a life.
A81: Becoming Led Zeppelin | D81: 1 | E81: Netflix | F81: 7.5 | G81: en | H81: The individual journeys of the four members of the band, as they move through the music scene of the 1960s, playing small clubs throughout Britain and performing some of the biggest hits of the era, until their meeting in the summer of 1968 for a rehearsal that changes their lives forever.
A82: Tatami | D82: 1 | E82: 14.99 | F82: 7.4 | G82: en | H82: Iranian female judokas Leila and her coach Maryam, travel to the Judo World Championship, intent on bringing home Iran’s first gold medal. Midway through the Judo World Championships, they receive an ultimatum from the Islamic Republic ordering Leila to fake an injury and lose, or she will be branded a traitor of the state. With her own and her family’s freedom at stake, Leila is faced with an impossible choice: comply with the Iranian regime as her coach Maryam implores her to do, or fight on, for the gold.
A83: Downton Abbey: The Grand Finale | D83: 1 | E83: Peacock | F83: 7.4 | G83: en | H83: When Mary finds herself at the center of a public scandal and the family faces financial strife, the entire household grapples with the threat of social disgrace. The Crawleys must embrace change as the staff prepares for a new chapter with the next generation leading Downton Abbey into the future.
A84: Cheech and Chong's Last Movie | D84: 1 | E84: 9.99 | F84: 7.3 | G84: en | H84: Exploring their 5-decade career performing stand-up, making records, and starring in hit films. It covers their lives, comedy partnership, and lasting influence on pop culture.
A85: To a Land Unknown | D85: 1 | E85: 12.99 | F85: 7.3 | G85: en | H85: Chatila and Reda are saving to pay for fake passports to get out of Athens. But when Reda loses their hard-earned cash to his dangerous drug addiction, Chatila hatches an extreme plan, which involves them posing as smugglers and taking hostages in an effort to get him and his best friend out of their hopeless environment before it is too late.
A86: One to One: John & Yoko | D86: 1 | E86: Max | F86: 7.3 | G86: en | H86: Set in 1972 New York, this documentary explores John and Yoko's world amid a turbulent era. Centered on the One to One charity concert for special needs children, it features unseen archives, home movies, and restored footage.
A87: Lilly | D87: 1 | E87: Netflix | F87: 7.3 | G87: en | H87: Based on the inspiring true story of Lilly Ledbetter, an ordinary Alabama tire factory supervisor who discovers she's being paid less than her male peers. Her fight for fair pay takes her to the Supreme Court and Congress, while powerful forces try to shut her down. Lilly refuses to accept the status quo and has the courage to fight for what is right.
A88: One Night in Tokyo | D88: 1 | E88: 5.99 | F88: 7.1 | G88: en | H88: Betrayal spawns an unexpected night through the streets of Tokyo for two strangers left questioning the meaning of life and love.
A89: Pavements | D89: 1 | E89: 7.99 | F89: 7.1 | G89: en | H89: '90s indie-rock band Pavement reunites for their sold-out 2022 tour. But as preparations get underway, surreal tributes emerge: an off-Broadway musical adaptation of their songs, a museum devoted entirely to the band’s legacy, and a shamelessly awards-baiting Hollywood biopic.
A90: Familiar Touch | D90: 1 | E90: 7.99 | F90: 7.1 | G90: en | H90: An octogenarian woman transitions to life in assisted living as she contends with her conflicting relationship to herself and her caregivers amidst her shifting memory, age identity, and desires.
A91: A Little Prayer | D91: 1 | E91: 12.99 | F91: 7.1 | G91: en | H91: A loving father grapples with how to protect his daughter-in-law when he discovers that his son is having an affair in a sensitive and searching portrait of a Southern family.
A92: Plainclothes | D92: 1 | E92: 12.99 | F92: 7.1 | G92: en | H92: A promising undercover agent assigned to lure and arrest gay men defies professional orders when he falls in love with a target.
A93: Stiller & Meara: Nothing is Lost | D93: 1 | E93: Apple | F93: 7.1 | G93: en | H93: Ben Stiller tells the story of his parents—comedy icons Jerry Stiller and Anne Meara—exploring their impact on popular culture and at home, where the lines between creativity, family, life, and art often blurred.
A94: The Ugly Stepsister | D94: 1 | E94: Hulu | F94: 7 | G94: no | H94: In a fairy-tale kingdom where beauty is a brutal business, Elvira battles to compete with her incredibly beautiful stepsister, and she will go to any length to catch the prince’s eye.
A95: Violent Ends | D95: 1 | E95: 12.99 | F95: 6.9 | G95: en | H95: Set in the Ozark Mountains, Lucas Frost is an honest man brought up in a crime family whose only legacy is violence. As Lucas tries to make a peaceful life of his own with his fiancée, Emma, he is suddenly pulled back into the family business when his cousin, Eli, perpetrates an armed robbery with brutal consequences.
A96: Magazine Dreams | D96: 1 | E96: 14.99 | F96: 6.9 | G96: en | H96: Aspiring bodybuilder Killian Maddox struggles to find human connection in this exploration of celebrity and violence. Nothing deters him from his fiercely protected dream of superstardom, not even the doctors who warn him of the permanent damage he causes to himself with his quest.
A97: Urchin | D97: 1 | E97: 14.99 | F97: 6.9 | G97: en | H97: Mike, a rough sleeper in London, is trapped in a cycle of self-destruction as he attempts to turn his life around. Along the way, he encounters unexpected chances for a fresh start.
A98: Unstoppable | D98: 1 | E98: Prime | F98: 6.8 | G98: en | H98: With the unwavering love and support of his devoted mother Judy and the encouragement of his coaches, Anthony Robles fights through adversity to earn a spot on the Arizona State Wrestling team. But it will demand everything he has, physically and mentally, to achieve his ultimate quest to become an NCAA Champion.
A99: Deathstalker | D99: 1 | E99: 5 | F99: 6.7 | G99: en | H99: The warrior Deathstalker is tasked by an old witch lady to obtain and unite the three powers of creation – a chalice, an amulet, and a sword – lest the evil magician Munkar get them and use them for nefarious purposes. After obtaining the sword, Deathstalker joins with other travelers going to the Big Tournament to determine the strongest warrior. The false king holds the true princess in captivity, and plots to have Deathstalker killed, and Deathstalker must fight to free the princess.
A100: Sarah's Oil | D100: 1 | E100: 19.99 | F100: 6.7 | G100: en | H100: Sarah Rector, an African-American girl born in Oklahoma Indian Territory in the early 1900s, believes there is oil beneath the barren land she’s allotted, and her faith is proven right. As greedy oil sharks close in, Sarah turns to her family, friends, and some Texas wildcatters to maintain control of her oil-rich land, eventually becoming among the nation's first female African-American millionaires—at eleven years old.
...

Sheet 2025 Awards
A1: A Big Bold Beautiful Journey | D1: Fantastic Four: First Steps, The | G1: One Battle After Another
A2: 6 | B2: 37 | C2: 58 | D2: 6.8 | E2: 86 | F2: 90 | G2: 7.7 | H2: 94 | I2: 85
A3: A House of Dynamite | D3: Frankenstein | G3: Phoenician Scheme, The
A4: 6.4 | B4: 75 | C4: 78 | D4: 7.4 | E4: 85 | F4: 94 | G4: 6.6 | H4: 77 | I4: 70
A5: A Working Man | D5: Friendship | G5: Psycho Therapy
A6: 5.7 | B6: 47 | C6: 87 | D6: 6.6 | E6: 88 | F6: 73 | G6: 6.2 | H6: 84 | I6: 58
A7: All of You | D7: Good Fortune | G7: Roofman
A8: 6.3 | B8: 72 | C8: 65 | D8: 6.5 | E8: 78 | F8: 81 | G8: 7 | H8: 87 | I8: 85
A9: Amateur, The | D9: Hamnet | G9: Running Man, The
A10: 6.5 | B10: 61 | C10: 87 | D10: 7.9 | E10: 87 | F10: 93 | G10: 6.4 | H10: 62 | I10: 78
A11: Anaconda | D11: Honey Don't! | G11: Secret Agent, The
A12: 5.6 | B12: 48 | C12: 75 | D12: 5.2 | E12: 45 | F12: 39 | G12: 7.3 | H12: 98 | I12: 82
A13: Another Simple Favor | D13: Housemaid, The | G13: Shark Whisperer
A14: 5.3 | B14: 58 | C14: 35 | D14: 6.8 | E14: 73 | F14: 92 | G14: 6.9 | I14: 78
A15: Avatar: Fire and Ash | D15: How to Train Your Dragon | G15: She Rides Shotgun
A16: 7.4 | B16: 66 | C16: 90 | D16: 7.7 | E16: 77 | F16: 97 | G16: 6.5 | H16: 88 | I16: 92
A17: Back in Action | D17: I Know What You Did Last Summer | G17: Sinners
A18: 5.9 | B18: 31 | C18: 60 | D18: 5.1 | E18: 46 | F18: 67 | G18: 7.5 | H18: 97 | I18: 96
A19: Bad Guys 2, The | D19: Is This Thing On? | G19: Sketch
A20: 7 | B20: 87 | C20: 94 | D20: 6.8 | E20: 87 | F20: 83 | G20: 6.6 | H20: 95 | I20: 83
A21: From the World of John Wick: Ballerina | D21: Jurassic World: Rebirth | G21: Snow White
A22: 6.8 | B22: 75 | C22: 92 | D22: 5.8 | E22: 50 | F22: 70 | G22: 2.2 | H22: 39 | I22: 69
A23: Baltimorons, The | D23: KPop Demon Hunters | G23: Sorry, Baby
A24: 6.9 | B24: 93 | C24: 84 | D24: 7.4 | E24: 91 | F24: 99 | G24: 7.1 | H24: 97 | I24: 85
A25: Black Bag | D25: Lilo & Stitch | G25: Springsteen: Deliver Me From Nowhere
A26: 6.7 | B26: 96 | C26: 70 | D26: 6.7 | E26: 72 | F26: 91 | G26: 6.6 | H26: 61 | I26: 82
A27: Bugonia | D27: Long Walk, The | G27: Superman
A28: 7.4 | B28: 87 | C28: 84 | D28: 6.7 | E28: 88 | F28: 85 | G28: 7 | H28: 83 | I28: 90
A29: Captain America: Brave New World | D29: Lost Bus, The | G29: Surfer, The
A30: 5.6 | B30: 46 | C30: 75 | D30: 6.8 | E30: 88 | F30: 95 | G30: 5.9 | H30: 84 | I30: 46
A31: Caught Stealing | D31: Love Hurts | G31: Thunderbolts*
A32: 6.9 | B32: 85 | C32: 83 | D32: 5.3 | E32: 18 | F32: 60 | G32: 7.1 | H32: 88 | I32: 93
A33: Code 3 | D33: Marty Supreme | G33: Thursday Murder Club, The
A34: 7.2 | B34: 78 | C34: 96 | D34: 7.8 | E34: 93 | F34: 82 | G34: 6.5 | H34: 77 | I34: 54
A35: Companion | D35: Mickey 17 | G35: Train Dreams
A36: 6.9 | B36: 93 | C36: 88 | D36: 6.7 | E36: 78 | F36: 73 | G36: 7.5 | H36: 94 | I36: 92
A37: Dangerous Animals | D37: Monkey, The | G37: Wake Up Dead Man: A Knives Out Mystery
A38: 6.4 | B38: 87 | C38: 74 | D38: 5.9 | E38: 77 | F38: 55 | G38: 7.3 | H38: 92 | I38: 94
A39: Day The Earth Blew Up: A Looney Tunes Movie, The | D39: Mountainhead | G39: Warfare
A40: 6.8 | B40: 86 | C40: 88 | D40: 5.4 | E40: 73 | F40: 27 | G40: 7.1 | H40: 92 | I40: 93
A41: Death of a Unicorn | D41: Naked Gun, The | G41: Weapons
A42: 5.8 | B42: 52 | C42: 76 | D42: 6.3 | E42: 87 | F42: 72 | G42: 7.4 | H42: 93 | I42: 85
A43: Eddington | D43: Nobody 2 | G43: Wicked: For Good
A44: 6.6 | B44: 69 | C44: 66 | D44: 6.3 | E44: 76 | F44: 88 | G44: 6.7 | H44: 66 | I44: 92
A45: Eephus | D45: Novocaine | G45: Woman in Cabin 10, The
A46: 6.7 | B46: 100 | C46: 64 | D46: 6.5 | E46: 81 | F46: 84 | G46: 5.8 | H46: 29 | I46: 32
A47: Elio | D47: Now You See Me: Now You Don't | G47: You're Cordially Invited
A48: 6.6 | B48: 83 | C48: 89 | D48: 5.9 | E48: 61 | F48: 79 | G48: 5.5 | H48: 48 | I48: 33
A49: F1: The Movie | D49: Nuremberg | G49: Zootopia 2
A50: 7.6 | B50: 82 | C50: 97 | D50: 7.4 | E50: 71 | F50: 95 | G50: 7.4 | H50: 91 | I50: 95
A51: Fackham Hall | D51: Oh, Hi!
A52: 6.4 | B52: 75 | C52: 76 | D52: 6.2 | E52: 64 | F52: 65

Sheet 2024
B1: Seen | C1: Own | D1: Want to see | E1: Where | F1: IMDb | G1: =SUM(B:B) -> 69 | H1: =_xlfn.CONCAT(SUM(C:C)," (",SUMPRODUCT(C:C,--(NOT(B:B=1))),")") -> 23 (15) | J1: 45657
A2: Dune: Part Two | B2: 1 | F2: 8.5 | G2: Science-Fiction, Drama, Action Adventure
A3: The Wild Robot | B3: 1 | F3: 8.2 | G3: Animation, Science-Fiction, Family Animation
A4: The Brutalist | B4: 1 | F4: 8.1 | G4: Drama
A5: Wicked: Part One | B5: 1 | F5: 8 | G5: Fantasy, Drama, Romance
A6: Anora | B6: 1 | F6: 7.9 | G6: Comedy, Drama, Romance, Emotional Drama, Dramedy
A7: Flow | B7: 1 | F7: 7.9 | G7: Animation, Fantasy, Action & Adventure, Kids & Family, Family Animation
A8: A Complete Unknown | B8: 1 | F8: 7.8 | G8: Drama, Music & Musical, History, Music Biopics
A9: Memoir of a Snail | B9: 1 | F9: 7.8 | G9: Animation, Drama, Claymation
A10: Nosferatu | B10: 1 | C10: 1 | F10: 7.8 | G10: Fantasy, Horror, Dark Fantasy
A11: Pixar's Inside Out 2 | B11: 1 | F11: 7.6 | G11: Animation, Action & Adventure, Comedy, Kids & Family, Drama, Fantasy, Family Animation
A12: Deadpool & Wolverine | B12: 1 | F12: 7.6 | G12: Action & Adventure, Comedy, Science-Fiction, Superhero
A13: A Real Pain | B13: 1 | F13: 7.6 | G13: Drama, Comedy, Dramedy
A14: Will & Harper | B14: 1 | F14: 7.5 | G14: Comedy, Documentary
A15: Nickel Boys | B15: 1 | F15: 7.5 | G15: Drama, Emotional Drama
A16: The Substance | B16: 1 | C16: 1 | F16: 7.4 | G16: Science-Fiction, Horror, Drama
A17: Conclave | B17: 1 | F17: 7.4 | G17: Drama, Mystery Thriller
A18: September 5 | B18: 1 | C18: 1 | F18: 7.1 | G18: Drama, History, Mystery & Thriller, Emotional Drama
A19: The Apprentice | B19: 1 | C19: 1 | F19: 7.1 | G19: History, Drama, Biopics
A20: Challengers | B20: 1 | F20: 7.1 | G20: Drama, Comedy, Romance, Sport, Sports Drama
A21: Saturday Night | B21: 1 | F21: 7.1 | G21: Drama, History, Comedy, Dramedy
A22: Thelma | B22: 1 | F22: 7 | G22: Comedy, Action & Adventure, Action Comedy
A23: Juror #2 | B23: 1 | F23: 7 | G23: Crime, Drama, Mystery Thriller
A24: Wicked Little Letters | B24: 1 | F24: 7 | G24: Comedy, Crime, Drama, History, Mystery & Thriller, Dramedy
A25: Civil War | B25: 1 | F25: 7 | G25: Action & Adventure, Mystery & Thriller, Drama, War Epics
A26: We Live in Time | B26: 1 | F26: 7 | G26: Drama, Romance, Romantic Drama
A27: Moana 2 | B27: 1 | F27: 7 | G27: Action & Adventure, Kids & Family, Comedy, Animation, Fantasy, Family Animation
A28: A Different Man | B28: 1 | F28: 7 | G28: Drama, Comedy, Mystery Thriller
A29: The Fall Guy | B29: 1 | F29: 6.9 | G29: Comedy, Drama, Romance, Action & Adventure, Action Comedy
A30: My Old Ass | B30: 1 | F30: 6.9 | G30: Romance, Comedy, Drama, Dramedy
A31: Monkey Man | B31: 1 | C31: 1 | F31: 6.8 | G31: Action & Adventure, Mystery & Thriller, Crime, Action Thriller
A32: The Ministry of Ungentlemanly Warfare | B32: 1 | F32: 6.8 | G32: Action & Adventure, Comedy, War & Military, War Drama
A33: Hit Man | B33: 1 | F33: 6.8 | G33: Comedy, Crime, Romance, Action Comedy
A34: Emilia Perez | B34: 1 | F34: 6.8 | G34: Drama, Mystery & Thriller, Comedy, Crime, Dark Crime
A35: That Christmas | B35: 1 | F35: 6.8 | G35: Action & Adventure, Animation, Comedy, Kids & Family, Fantasy, Holiday, Family Animation
A36: Mufasa: The Lion King | B36: 1 | F36: 6.8 | G36: Drama, Kids & Family, Fantasy, Animation, Music & Musical, Action & Adventure, Family Animation
A37: The Bikeriders | B37: 1 | C37: 1 | F37: 6.7 | G37: Crime, Drama, Organized Crime
A38: Beetlejuice Beetlejuice | B38: 1 | F38: 6.7 | G38: Horror, Comedy, Fantasy, Horror Comedy
A39: Gladiator II | B39: 1 | F39: 6.7 | G39: Drama, Action Adventure
A40: It's What's Inside | B40: 1 | F40: 6.6 | G40: Science-Fiction, Comedy, Mystery & Thriller, SciFi Horror
A41: Woman of the Hour | B41: 1 | F41: 6.6 | G41: Crime, Drama, Mystery Thriller
A42: Fly Me to the Moon | B42: 1 | F42: 6.6 | G42: Romance, Comedy, RomCom
A43: Twisters | B43: 1 | C43: 1 | F43: 6.5 | G43: Mystery & Thriller, Disaster, Action Adventure
A44: Wolfs | B44: 1 | F44: 6.5 | G44: Crime, Comedy, Action & Adventure, Mystery & Thriller, Action Comedy
A45: Blink Twice | B45: 1 | F45: 6.5 | G45: Horror, Mystery & Thriller, Dramedy
A46: Carry-On | B46: 1 | F46: 6.5 | G46: Action & Adventure, Crime, Drama, Action Thriller, Mystery Thriller
A47: Boy Kills World | B47: 1 | F47: 6.4 | G47: Crime, Mystery & Thriller, Action & Adventure, Action Thriller
A48: IF - Imaginary Friend | B48: 1 | F48: 6.4 | G48: Animation, Comedy, Drama, Kids & Family, Fantasy, Live Action, Modern Fantasy, Dramedy
A49: Red One | B49: 1 | F49: 6.4 | G49: Action & Adventure, Fantasy, Comedy, Action Comedy
A50: Babes | B50: 1 | F50: 6.3 | G50: Comedy, Dramedy
A51: A Quiet Place: Day One | B51: 1 | F51: 6.3 | G51: Horror, Science-Fiction, Mystery & Thriller, Drama, SciFi Horror
A52: Greedy People | B52: 1 | C52: 1 | F52: 6.2 | G52: Comedy, Crime, Mystery & Thriller, Action Comedy
A53: Bob Marley: One Love | B53: 1 | F53: 6.2 | G53: History, Drama, Music & Musical, Music Biopics
A54: Despicable Me 4 | B54: 1 | F54: 6.2 | G54: Kids & Family, Comedy, Science-Fiction, Animation, Crime, Family Animation
A55: Here | B55: 1 | F55: 6.2 | G55: Drama, Emotional Drama
A56: Sleeping Dogs | B56: 1 | F56: 6.1 | G56: Crime, Drama, Mystery Thriller
A57: Ghostbusters: Frozen Empire | B57: 1 | F57: 6.1 | G57: Fantasy, Comedy, Science-Fiction, Horror Comedy, Sci-Fi Comedy, Action Adventure, Action Comedy
A58: Godzilla x Kong: The New Empire | B58: 1 | F58: 6.1 | G58: Science-Fiction, Mystery & Thriller, Action & Adventure, Fantasy, Invasion
A59: Venom: The Last Dance | B59: 1 | F59: 6 | G59: Mystery & Thriller, Science-Fiction, Action Adventure
A60: Trap | B60: 1 | F60: 5.9 | G60: Mystery & Thriller, Crime, Horror, Horror Thriller
A61: Nightbitch | B61: 1 | F61: 5.8 | G61: Horror, Fantasy, Comedy, Horror Comedy
A62: The Garfield Movie | B62: 1 | F62: 5.7 | G62: Action & Adventure, Animation, Comedy, Kids & Family, Fantasy, Family Animation
A63: The Watchers | B63: 1 | F63: 5.7 | G63: Mystery & Thriller, Horror, Fantasy, Horror Thriller, Dark Fantasy
A64: Argylle | B64: 1 | F64: 5.6 | G64: Comedy, Mystery & Thriller, Action Adventure
... A70: Joker: Folie à Deux | B70: 1 | F70: 5.2 | G70: Drama, Mystery & Thriller, Crime, Dark Crime
A71: The Last of the Sea Women | D71: 1 | E71: Apple | F71: 7 | G71: Documentary
A72: Fancy Dance | D72: 1 | E72: Apple | F72: 6.6 | G72: Drama, Emotional Drama
A73: The Instigators | D73: 1 | E73: Apple | F73: 6.2 | G73: Crime, Comedy, Action & Adventure, Drama, Mystery & Thriller, Action Comedy
A74: Blitz | D74: 1 | E74: Apple | F74: 6.2 | G74: Action & Adventure, Drama, History, War & Military, War Drama
A75: Music by John Williams | D75: 1 | E75: Disney | F75: 8.2 | G75: Documentary, Music & Musical, Music Biopics
A76: Jim Henson Idea Man | D76: 1 | E76: Disney | F76: 7.7 | G76: Documentary
A77: Young Woman and the Sea | D77: 1 | E77: Disney | F77: 7.5 | G77: Drama, Romance, Sport, Biopics
A78: Endurance | D78: 1 | E78: Disney | F78: 7.5 | G78: Documentary
A79: Out of My Mind | D79: 1 | E79: Disney | F79: 7.4 | G79: Drama, Emotional Drama
A80: Beatles '64 | D80: 1 | E80: Disney | F80: 7.2 | G80: Music & Musical, Documentary, Music Biopics
A81: The Promised Land | D81: 1 | E81: Hulu | F81: 7.7 | G81: Drama, History, Action & Adventure, Biopics
A82: Femme | D82: 1 | E82: Hulu | F82: 7.3 | G82: Drama, Mystery Thriller
... A89: Suncoast | D89: 1 | E89: Hulu | F89: 6.7 | G89: Drama, Comedy, Emotional Drama
A90: My Penguin Friend | C90: 1 | D90: 1 | E90: Hulu | F90: 6.7 | G90: Drama, Kids & Family, Action & Adventure, Emotional Drama
A91: Kinds of Kindness | D91: 1 | E91: Hulu | F91: 6.5 | G91: Comedy, Drama, Horror, Dramedy
A92: Firebrand | D92: 1 | E92: Hulu | F92: 6.3 | G92: Drama, History, Mystery & Thriller, Period Drama
A93: Mayhem! | D93: 1 | E93: Hulu | F93: 6.3 | G93: Crime, Drama, Action & Adventure, Mystery & Thriller, Action Thriller
A94: Mothers' Instinct | D94: 1 | E94: Hulu | F94: 6.3 | G94: Drama, Emotional Drama, Mystery Thriller
A95: Marmalade | D95: 1 | E95: Hulu | F95: 6.2 | G95: Mystery & Thriller, Romance, Comedy, Crime, Drama, Dramedy
A96: Coup! | D96: 1 | E96: Hulu | F96: 6.1 | G96: Comedy, Mystery & Thriller, Crime, Drama, Dramedy
A97: The Silent Hour | D97: 1 | E97: Hulu | F97: 6 | G97: Action & Adventure, Crime, Mystery & Thriller, Detective Crime
A98: Scrambled | D98: 1 | E98: Hulu | F98: 5.9 | G98: Comedy, Female Comedy
A99: Immaculate | C99: 1 | D99: 1 | E99: Hulu | F99: 5.8 | G99: Horror, Mystery & Thriller, Horror Thriller
A100: Super/Man: The Christopher Reeve Story | D100: 1 | E100: Max | F100: 8.1 | G100: Documentary
A101: The Great Lillian Hall | D101: 1 | E101: Max | F101: 7.4 | G101: Drama, Emotional Drama
A102: The Commandant's Shadow | D102: 1 | E102: Max | F102: 7.3 | G102: Documentary, History, War & Military
A103: Knox Goes Away | D103: 1 | E103: Max | F103: 7 | G103: Crime, Mystery & Thriller, Action & Adventure, Action Thriller
A104: Caddo Lake | D104: 1 | E104: Max | F104: 6.9 | G104: Drama, Horror, Mystery Thriller
A105: Problemista | D105: 1 | E105: Max | F105: 6.8 | G105: Comedy, Raunchy Comedy
A106: Love Lies Bleeding | D106: 1 | E106: Max | F106: 6.6 | G106: Crime, Mystery & Thriller, Romance, Action & Adventure, Action Thriller
A107: Tuesday | D107: 1 | E107: Max | F107: 6.3 | G107: Fantasy, Drama, Modern Fantasy
A108: MaXXXine | D108: 1 | E108: Max | F108: 6.3 | G108: Mystery & Thriller, Horror, Crime, Horror Thriller
A109: Salem's Lot | D109: 1 | E109: Max | F109: 5.6 | G109: Horror, Mystery & Thriller, Horror Thriller
A110: Sweethearts | D110: 1 | E110: Max | F110: 5.6 | G110: Romance, Comedy, RomCom
A111: Remembering Gene Wilder | D111: 1 | E111: Netflix | F111: 7.8 | G111: Documentary
...

Sheet 2024 Awards
A1: A Complete Unknown | D1: Dune: Part Two | G1: Nickel Boys
A2: 7.5 | B2: 81 | C2: 95 | D2: 8.5 | E2: 92 | F2: 95 | G2: 7.5 | H2: 91 | I2: 75
A3: A Different Man | D3: Emilia Perez | G3: Nightbitch
A4: 6.9 | B4: 93 | C4: 89 | D4: 5.4 | E4: 72 | F4: 16 | G4: 5.6 | H4: 59 | I4: 47
A5: A Family Affair | D5: Fall Guy, The | G5: Pixar's Inside Out 2
A6: 5.3 | B6: 35 | C6: 30 | D6: 6.8 | E6: 82 | F6: 85 | G6: 7.5 | H6: 91 | I6: 95
A7: A Quiet Place: Day One | D7: Flow | G7: Red One
A8: 6.3 | B8: 86 | C8: 72 | D8: 7.9 | E8: 97 | F8: 98 | G8: 6.3 | H8: 30 | I8: 90
A9: A Real Pain | D9: Fly Me to the Moon | G9: Saturday Night
A10: 7.1 | B10: 96 | C10: 81 | D10: 6.6 | E10: 65 | F10: 89 | G10: 6.9 | H10: 78 | I10: 84
A11: Anora | D11: Garfield Movie, The | G11: September 5
A12: 7.7 | B12: 93 | C12: 89 | D12: 5.7 | E12: 37 | F12: 79 | G12: 7.1 | H12: 93 | I12: 90
A13: Apprentice, The | D13: Ghostbusters: Frozen Empire | G13: Sleeping Dogs
A14: 7.1 | B14: 83 | C14: 84 | D14: 6.1 | E14: 42 | F14: 82 | G14: 6.2 | H14: 42 | I14: 82
A15: Argylle | D15: Gladiator II | G15: Substance, The
A16: 5.6 | B16: 33 | C16: 70 | D16: 6.6 | E16: 71 | F16: 82 | G16: 7.3 | H16: 90 | I16: 75
A17: Babes | D17: Godzilla x Kong: The New Empire | G17: That Christmas
A18: 6.3 | B18: 88 | C18: 78 | D18: 6.1 | E18: 54 | F18: 90 | G18: 6.8 | H18: 67 | I18: 74
A19: Beetlejuice Beetlejuice | D19: Greedy People | G19: Thelma
A20: 6.7 | B20: 75 | C20: 79 | D20: 6.2 | E20: 60 | F20: 57 | G20: 7 | H20: 98 | I20: 83
A21: Bikeriders, The | D21: Here | G21: Trap
A22: 6.6 | B22: 80 | C22: 74 | D22: 6.3 | E22: 37 | F22: 53 | G22: 5.8 | H22: 57 | I22: 65
A23: Blink Twice | D23: Hit Man | G23: Twisters
A24: 6.5 | B24: 75 | C24: 71 | D24: 6.8 | E24: 95 | F24: 91 | G24: 6.5 | H24: 75 | I24: 90
A25: Bob Marley: One Love | D25: IF - Imaginary Friend | G25: Unfrosted
A26: 6.2 | B26: 43 | C26: 91 | D26: 6.4 | E26: 50 | F26: 86 | G26: 5.5 | H26: 40 | I26: 50
A27: Boy Kills World | D27: It's What's Inside | G27: Venom: The Last Dance
A28: 6.4 | B28: 58 | C28: 73 | D28: 6.6 | E28: 79 | F28: 69 | G28: 6 | H28: 40 | I28: 80
A29: Brutalist, The | D29: Joker: Folie à Deux | G29: Watchers, The
A30: 7.6 | B30: 94 | C30: 80 | D30: 5.2 | E30: 31 | F30: 31 | G30: 5.7 | H30: 33 | I30: 50
A31: Carry-On | D31: Juror #2 | G31: We Live in Time
A32: 6.5 | B32: 87 | C32: 51 | D32: 7 | E32: 93 | F32: 91 | G32: 7 | H32: 79 | I32: 83
A33: Challengers | D33: Kraven the Hunter | G33: Wicked Little Letters
A34: 7.1 | B34: 88 | C34: 75 | D34: 5.4 | E34: 16 | F34: 73 | G34: 7 | H34: 80 | I34: 92
A35: Civil War | D35: Memoir of a Snail | G35: Wicked: Part One
A36: 7 | B36: 81 | C36: 69 | D36: 7.8 | E36: 95 | F36: 82 | G36: 7.6 | H36: 88 | I36: 95
A37: Conclave | D37: Ministry of Ungentlemanly Warfare, The | G37: Wild Robot, The
A38: 7.4 | B38: 93 | C38: 86 | D38: 6.8 | E38: 68 | F38: 92 | G38: 8.2 | H38: 96 | I38: 98
A39: Deadpool & Wolverine | D39: Moana 2 | G39: Will & Harper
A40: 7.6 | B40: 78 | C40: 94 | D40: 6.8 | E40: 61 | F40: 86 | G40: 7.4 | H40: 99 | I40: 81
A41: Dear Santa | D41: Monkey Man | G41: Wolfs
A42: 5.4 | B42: 24 | C42: 39 | D42: 6.8 | E42: 89 | F42: 82 | G42: 6.5 | H42: 67 | I42: 71
A43: Despicable Me 4 | D43: Mufasa: The Lion King | G43: Woman of the Hour
A44: 6.2 | B44: 56 | C44: 87 | D44: 6.7 | E44: 57 | F44: 89 | G44: 6.6 | H44: 91 | I44: 68
A45: Drive-Away Dolls | D45: My Old Ass
A46: 5.4 | B46: 63 | C46: 36 | D46: 6.9 | E46: 90 | F46: 89

Sheet 2023
B1: Seen | C1: Own | D1: Want to see | E1: Where | F1: IMDb | G1: =SUM(B:B) -> 59 | H1: =_xlfn.CONCAT(SUM(C:C)," (",SUMPRODUCT(C:C,--(NOT(B:B=1))),")") -> 22 (13)
A2: No Hard Feelings | B2: 1 | C2: 1 | E2: Netflix | F2: 6.4 | G2: Comedy, Romance | H2: Maddie is working as an Uber driver in Montauk, New York. She’s already struggling to make ends meet but when her car gets repossessed she looks set to face bankruptcy if she can’t find a solution. Desperate for something, she accepts an unusual posting on Craigslist that would win her a Buick Regal. In exchange for the car, she needs to date Percy, the introverted son of the helicopter parents behind the ad. Hoping to bring him out of his social seclusion, the parents agree that Maddie will seduce him and become Percy’s girlfriend in order to teach him about adult life. But unleashing the full force of Percy’s pent-up adolescence has consequences no one could imagine.
A3: Barbie | B3: 1 | C3: 1 | E3: Plex | F3: 7 | G3: Action & Adventure, Fantasy, Comedy | H3: When Barbie leaves Barbieland and finds herself in the real world, she's a fish out of water longing for her old life. Meanwhile, her boyfriend Ken seems at ease with the impossible standards of the human world. Can their relationship survive this clash of ideals?
A4: Asteroid City | B4: 1 | C4: 1 | E4: Plex | F4: 6.6 | G4: Comedy, Drama, Romance, Science-Fiction | H4: Asteroid City is the science-loving American’s top holiday destination. This small desert town plays host to the 1955 Junior Stargazer and Space Cadet conventions. In the dusty desert heat, sudden spectacular events interrupt the program and put Asteroid City on the map.
A5: Cocaine Bear | B5: 1 | C5: 1 | E5: Plex | F5: 5.9 | G5: Mystery & Thriller, Comedy, Crime | H5: Cocaine Bear is the story of just that: a black bear who somehow gets his hands on a massive amount of cocaine and swallows it. The result is a drug-fueled rampage of mayhem and murder.
A6: Oppenheimer | B6: 1 | C6: 1 | F6: 8.4 | G6: Drama, History | H6: The film tells the tale of J. Robert Oppenheimer, a theoretical physicist. Oppenheimer was a leading figure of the Manhattan Project – a codename for the effort to develop weapons strong enough to lead the Allied Forces to victory and tightly secure the United States role as a world’s super power. The events of the film take place during the Second World War while Oppenheimer worked for the Los Alamos Laboratory where the bombs were created.
A7: John Wick: Chapter 4 | B7: 1 | C7: 1 | F7: 7.7 | G7: Action & Adventure, Mystery & Thriller, Crime | H7: Before he can earn his freedom, Wick must face off against a new enemy with powerful alliances across the globe and forces that turn old friends into foes.
A8: Disney's Wish | B8: 1 | C8: 1 | F8: 5.8 | G8: Action & Adventure, Animation, Kids & Family, Fantasy, Comedy | H8: Asha is a teenager living in the Kingdom of Rosas. She senses uncommon darkness in the ruler King Magnifico. She pleads to the night sky for help in understanding and is shocked when it answers. A star called Star falls from above and answers her wish. Together Asha and Star must find a way to battle the oncoming darkness and save the people of Rosas.
A9: Tetris | B9: 1 | E9: Apple | F9: 7.4 | G9: Drama, History, Mystery & Thriller | H9: Henk Rogers is a video games publisher who has found the perfect game – Tetris. The only problem is, that it is designed and created by Alexey Pajitnov, a Russian computer engineer. In the midst of the Cold War, the pair seek to bring the game to an international audience and risk diplomatic and commercial disaster in the process. The legal battle winds up involving Hiroshi Yamauchi, president of Nintendo, British media mogul, Robert Maxwell, countless KGB agents, and even Mikhail Gorbachev himself. This high-stakes thriller is the story of one man’s mission to bring the most addictive video game to millions of households around the world.
A10: Guardians of the Galaxy Vol. 3 | B10: 1 | E10: Disney | F10: 7.9 | G10: Action & Adventure, Comedy, Science-Fiction | H10: As Rocket's past comes back to haunt him, he finds himself in mortal danger. In order to save his life, the Guardians must band together and leave the comfort of their new home on Knowhere. With new villains always on the horizon and long-expected Marvel favourite Adam Warlock making his debut in the Marvel Cinematic Universe (MCU), the Guardians of the Galaxy have their work cut out for them in this third instalment.
A11: The Little Mermaid | B11: 1 | E11: Disney | F11: 7.2 | G11: Action & Adventure, Kids & Family, Fantasy, Romance | H11: Ariel is the daughter of King Triton, a proud ruler of the underwater Atlantica kingdom. Wary and prejudiced against the humans above the surface, King Triton doesn’t understand his daughters deep fascination with the human world. The young princess is cunning and rebellious. She is not content to stay in Atlantica and wants to experience the human world. Her curiosity however plays into the hands of the sly and seditious sea-witch Ursula, who plots to take over Atlantica herself. When Ariel saves the life of Prince Eric, a human man drowning in the sea, the two fall in love and the stage is set. Ursula offers Ariel a trade: she will make the princess human in exchange for her beautiful singing voice.
A12: Pixar's Elemental | B12: 1 | E12: Disney | F12: 7 | G12: Comedy, Kids & Family, Fantasy, Romance, Animation, Drama, Science-Fiction | H12: This touching tale is set in a city where the residents personify each of the elements; water, fire, air, and land. Ember is a passionate and fiery go-getter while Wade likes to take things as they come and go with the flow. Some elements mix better than others and as they face their differences they begin to see just how much they have in common.
A13: Ant-Man and the Wasp: Quantumania | B13: 1 | E13: Disney | F13: 6.1 | G13: Science-Fiction, Action & Adventure, Comedy | H13: After battling through the quantum realm in their last outing together, Ant-Man and the Wasp: Quantumania sees the duo return for their third instalment to face down a new challenge. Scott Lang and Hope Pym are reunited to tackle their most difficult adversary yet, the time-travelling, multiverse villain, Kang the Conqueror.
A14: Disney's Haunted Mansion | B14: 1 | E14: Disney | F14: 6.1 | G14: Comedy, Horror, Kids & Family, Fantasy, Drama | H14: Gabbie has found the perfect home for her and her son, which promises a new beginning for them in New Orleans. But the new move isn’t a smooth one. There are strange and inexplicable things starting to happen. Could the house be haunted with dark spirits? To find out and hopefully rid herself of the supernatural beings, she enlists the help of several people, including a priest, a psychic, a historian, and a paranormal expert.
A15: Quiz Lady | B15: 1 | E15: Hulu | F15: 6.7 | G15: Comedy | H15: A brilliant but tightly wound, gameshow-obsessed young woman, Anne, and her estranged, train-wreck of a sister Jenny, must work together to help cover their mother’s gambling debts. When Anne’s beloved dog is kidnapped, they set out on a wild, cross-country trek to get the cash the only way they know how: by turning Anne into a bona-fide gameshow champion.
A16: To Catch a Killer | B16: 1 | E16: Hulu | F16: 6.6 | G16: Mystery & Thriller, Crime, Drama, Action & Adventure | H16: Baltimore. New Year's Eve. A talented but troubled police officer is recruited by the FBI's chief investigator to help profile and track down a mass murderer.
A17: A Haunting in Venice | B17: 1 | E17: Hulu | F17: 6.5 | G17: Mystery & Thriller, Crime, Drama, Horror | H17: Hercule Poirot is trying to enjoy a quiet retirement in Venice when he is invited to a seance at a haunted palazzo. As things take a turn for the supernatural, the mustachioed detective must use his powers of observation to discover the true intentions of the group, who are gathered to connect to the dead. A murder, a disappearance, and a history of strange happenings in the area all connect in one of Poirot’s scariest cases yet.
A18: The Flash | B18: 1 | E18: Max | F18: 6.7 | G18: Science-Fiction, Action & Adventure, Fantasy | H18: The speedster decides to use his superhuman pace to travel back in time and prevent his mother from dying. But his move has unexpected and chaotic consequences. The Flash finds himself stuck in a reality where the evil General Zod has re-emerged and no superheroes exist to challenge him. The Flash must rally with what allies he can find. Between a retired Batman, another Barry Allen, and a locked-up Supergirl, The Flash has friends, but does he have the time to save this world from certain destruction?
A19: Blue Beetle | B19: 1 | E19: Max | F19: 6 | G19: Action & Adventure, Science-Fiction, Mystery & Thriller | H19: Jaime Reyes is a freshly graduated college student returning home to a new life. Facing new challenges and struggles, Jaime must find his purpose and position in society. What he doesn't know is that destiny has a plan for him. When a mysterious ancient scarab attaches to his spine, it gives him the ability to travel through space in blue alien armor. Suddenly the host of this symbiotic power, Jaime becomes a superhero protected and powered by this alien technology.
A20: Meg 2: The Trench | B20: 1 | E20: Max | F20: 5 | G20: Action & Adventure, Science-Fiction, Horror, Mystery & Thriller | H20: No place on Earth is deeper than the Mariana Trench and at that depth, in the darkest most uninhabitable place on the planet, something is lurking. Jonas Taylor is back and facing a larger more terrifying shark than ever before. The ex-rescue diver has already faced down a prehistoric Megalodon and at great personal cost. Now the ancient beast returns, stronger, smarter, and more daring than ever. With a new crew assembled, featuring some familiar faces, Taylor will struggle to save them all from the jaws of the giant shark set upon destruction and mayhem.
... A40: Candy Cane Lane | B40: 1 | E40: Prime | F40: 5.6 | G40: Comedy, Fantasy, Kids & Family | H40: A man, determined to win the neighborhood's annual Christmas decorating contest, makes a pact with an elf to help him win. However, the elf casts a spell bringing the twelve days of Christmas to life, bringing chaos to the small, unsuspecting town.
A41: Poor Things | B41: 1 | F41: 8.5 | G41: Science-Fiction, Comedy, Fantasy, Drama, Romance | H41: Having already died and been brought back to life by an eccentric scientist, Bella is a truly unusual woman. Living under the guardianship of her creator, Dr. Godwin Baxter, Bella is hungry to learn about the world around her. When she meets a charming but ultimately flawed lawyer, she escapes his care to travel around the globe. Undefined by ideas of what a woman should be, Bella is free to challenge the social norms of the day and live her life as a liberated being.
A42: Past Lives | B42: 1 | F42: 8 | G42: Romance, Drama | H42: Nora and Hae Sung were deeply connected childhood friends torn apart when Nora and her family emigrated from South Korea. 20 years on, Nora is living in the United States and is married to Arthur, a white American. When Nora learns that Hae Sung has been searching for her, the two rekindle their connection. As they meet each other again the pair struggle to draw the line between who they are and who they could have been.
A43: The Holdovers | B43: 1 | C43: 1 | F43: 8 | G43: Comedy, Drama | H43: Nobody at Barton Academy likes Paul Hunham – a history teacher who is tired of the world and everyone in it. But when he’s put in charge of students who have nowhere to go over Christmas, Paul faces a new and unprecedented challenge – how to care for students who are living without a happy home to return to. Angus is one of those. Grieving the loss of his father, Angus is a holdover at Barton Academy and is being taken care of by Paul. The pair must learn how to understand each other if they are to survive the Holiday period.
A44: Killers of the Flower Moon | B44: 1 | F44: 7.9 | G44: Drama, Western, Crime, History, Romance | H44: A murder mystery surrounding members of the Osage tribe unfolds in 1920s America. The Native-American tribe, who reside in Oklahoma, were targeted after oil was discovered on their ancestral land. The case marks one of the first major investigations by the new Federal Bureau of Investigation (FBI) and shines a light on the notorious J. Edgar Hoover.
A45: Saltburn | B45: 1 | F45: 7.5 | G45: Comedy, Drama, Mystery & Thriller | H45: Oliver Quick is struggling to find his place in the aristocratic world of Oxford University. As he wrestles with his desire to fit in, he finds himself drawn to Felix Catton, a wealthy student from a prestigious family. When Oliver is invited to Saltburn, the family’s expansive estate, he gets mixed up in the strange and alluring world of the wealthy.
A46: The Hunger Games: The Ballad of Songbirds & Snakes | B46: 1 | F46: 7.1 | G46: Science-Fiction, Mystery & Thriller, War & Military, Action & Adventure, Drama, Romance | H46: Coriolanus Snow was not always the tyrannical and ruthless president he would become. Born into a family of high-status but decreasing wealth, Snow must use his charisma and intelligence to forge a path. A top student at the Academy in Panem, Snow became the mentor for District 12’s tribute Lucy Gray Baird and ot would not be the last time a tribute from District 12 would have a huge impact on the life of Coriolanus Snow. Set before the time of Katniss Everdeen and the resulting Hunger Games stories, The Ballad of Songbirds & Snakes tells the story of a young Snow training Lucy Gray to be victorious in the Hunger Games and as their relationship develops so too does his thirst for control and power, charting his rise to the top.
A47: Dumb Money | B47: 1 | F47: 6.9 | G47: Comedy, Drama, History | H47: A group of rogue investors who discuss their trades on the Reddit page, Wall Street Bets become the center of a huge controversy. The unlikely rabble manages a shocking short squeeze on two major hedge funds by betting on the fate of consumer electronics brand GameStop.
A48: The Creator | B48: 1 | F48: 6.9 | G48: Action & Adventure, Drama, Science-Fiction, Mystery & Thriller | H48: In a conflict between human beings and the mechanized battalions of artificial intelligence, Joshua is on a secret mission. The former special agent is on a covert mission to kill the Creator, the one who designed and built the advanced AI seeking to end human existence. Grieving for his lost wife, Joshua is searching for a new weapon that has been developed to end the war once and for all. But once he finds it, things become more complicated than they first seemed.
A49: Napoleon | B49: 1 | F49: 6.6 | G49: Drama, History, War & Military, Action & Adventure | H49: Napoleon Bonaparte came from nothing and rose through the ranks of the military to become the Emperor of France. Conquering all in his wake, the brilliant military strategist won battle after battle with his pure lust for power. But at the heart of his relentless conquest was his tempestuous relationship with the Empress Josephine. Their volatile love reveals a man ruled by his passions and whims leading eventually to his downfall.
A50: Plane | B50: 1 | F50: 6.5 | G50: Action & Adventure, Mystery & Thriller | H50: After a heroic job of successfully landing his storm-damaged aircraft in a war zone, a fearless pilot finds himself between the agendas of multiple militias planning to take the plane and its passengers hostage.
A51: The Marvels | B51: 1 | F51: 5.9 | G51: Science-Fiction, Action & Adventure, Fantas | H51: Carol Danvers has been busy battling galactic threats off-world as Captain Marvel. While investigating a wormhole in outer space, she becomes inextricably linked to her niece (Monica Rambeau) and her biggest superfan (Kamala Khan). While Captain Marvel usually flies solo, this cosmic coincidence forces her to work with others to save the universe from the threat of the Kree.
A52: Freelance | B52: 1 | F52: 5.4 | G52: Comedy, Action & Adventure | H52: An ex-special forces operative takes a job to provide security for a journalist as she interviews a dictator, but when a military coup breaks out in the middle of the interview, they are forced to escape into the jungle.
A53: American Fiction | B53: 1
A54: Wonka | B54: 1
A55: Anyone But You | B55: 1
A56: Aquaman and the Lost Kingdom | B56: 1
A57: Migration | B57: 1
A58: The Iron Claw | B58: 1 | C58: 1
A59: The Boys in the Boat | B59: 1
A60: The Retirement Plan | B60: 1
A61: The Covenant | C61: 1 | D61: 1 | E61: Plex | F61: 7.5 | G61: Action & Adventure, Mystery & Thriller, War & Military, Drama | H61: US Army Sergeant John Kinley cannot forget the kindness shown to him by his Afghan interpreter Ahmed. When Kinley is ambushed and left to die, Ahmed carries his body across harsh terrain in order to save his life. Safely returned to the US, Kinley owes Ahmed a great debt. When the Army Sergeant learns that Ahmed and his family were never given safe passage to the US as they were promised, he begins a chain of events that leads him to fulfill his pledge, his bond, and his commitment.
A62: Dream Scenario | C62: 1 | D62: 1 | E62: Plex | F62: 7.4 | G62: Comedy, Horror, Fantasy | H62: Paul Matthews is a professor who settled for a plain life as a hard-working family man. But when more and more strangers begin to recognize him as a figure from their dreams, Paul’s life takes a strange turn. He becomes increasingly famous and millions more people start seeing him in their dreams. But when those dreams turn to nightmares and Paul is still appearing in the sleeping minds of the nation, his own fame begins to take a toll.
A63: Champions | C63: 1 | D63: 1 | E63: Plex | F63: 6.8 | G63: Drama, Sport, Comedy | H63: A former minor-league basketball coach is ordered by the court to manage a team of players with intellectual disabilities. He soon realizes that despite his doubts, together, this team can go further than they ever imagined.
A64: Creed III | C64: 1 | D64: 1 | E64: Plex | F64: 6.7 | G64: Drama, Action & Adventure, Sport | H64: At the top of his game, boxing superstar Adonis Creed is flourishing. It seems that nothing can throw him off balance, until he meets Damian, an old childhood friend. Having served a prison sentence, Damian emerges back into the world of professional boxing as a ferocious and talented contender. For both men, this is bigger than boxing, but the bout can only be settled in the ring.
A65: You Hurt My Feelings | C65: 1 | D65: 1 | E65: Plex | F65: 6.6 | G65: Comedy, Drama, Romance | H65: A novelist's longstanding marriage is suddenly upended when she overhears her husband giving his honest reaction to her latest book.
A66: Ruby Gillman, Teenage Kraken | C66: 1 | D66: 1 | E66: Plex | F66: 5.7 | G66: Kids & Family, Fantasy, Animation, Action & Adventure, Comedy | H66: Ruby Gillman wants to be an ordinary teenager at Oceanside High. But when she learns that she descends from a line of powerful royal krakens, it becomes clear that she is anything but normal. Ruby will one day become the Warrior Queen of the Seven Seas, protecting the oceans from the vanity of her sworn adversaries, the mermaids. But before she can do that, she needs to face the newest, most popular girl at school, Chelsea who also just happens to be a mermaid.
A67: Marlowe | C67: 1 | D67: 1 | E67: Plex | F67: 5.3 | G67: Mystery & Thriller, Crime | H67: Private detective Philip Marlowe becomes embroiled in an investigation involving a wealthy Californian family after a beautiful blonde hires him to track down her former lover.
A68: House Party | C68: 1 | D68: 1 | E68: Plex | F68: 4.4 | G68: Comedy | H68: Aspiring club promoters and best buds Damon and Kevin are barely keeping things together. Out of money, down on their luck and about to lose the roofs over their heads—and freshly fired from their low-lift jobs as house cleaners—the pair needs a huge windfall to make their problems go away. In a ‘what the hell?’ move, they decide to host the party of the year at an exclusive mansion, the site of their last cleaning job, which just happens to belong to none other than LeBron James. No permission? No problem. What could go wrong?
A69: Ferrari | C69: 1 | D69: 1 | E69: Plex
A70: Flamin' Hot | D70: 1 | E70: Disney | F70: 6.9 | G70: Comedy, Drama, History | H70: The inspiring true story of Richard Montañez, the Frito Lay janitor who channeled his Mexican American heritage and upbringing to turn the iconic Flamin’ Hot Cheetos into a snack that disrupted the food industry and became a global pop culture phenomenon.
A71: Indiana Jones and the Dial of Destiny | D71: 1 | E71: Disney | F71: 6.6 | G71: Science-Fiction, Action & Adventure | H71: The witty professor of archaeology is set up for a new adventure. Set in the 1960s, Indy will face a resurgent Nazi threat and as always, he’ll have a team of trusted associates alongside him to uncover the mystery at the heart of the story. Alongside his Goddaughter Helena, and in the midst of the space race that features prominent ex-Nazis, Indy is drawn out from his quiet life to bring his trademark wit and whip to a whole new conspiracy.
A72: Pinball: The Man Who Saved the Game | D72: 1 | E72: Hulu | F72: 7 | G72: History, Romance, Comedy, Drama | H72: The dramatic comedy is based on the true story of writer and pinball wizard Roger Sharpe, chronicling his journey to overturn New York City’s 35-year ban on pinball.
A73: How to Blow Up a Pipeline | D73: 1 | E73: Hulu | F73: 7 | G73: Mystery & Thriller, Action & Adventure, Crime, Drama | H73: A crew of young environmental activists execute a daring mission to sabotage an oil pipeline.
A74: Saint Omer | D74: 1 | E74: Hulu | F74: 6.8 | G74: A novelist attends the trial of a woman accused of killing her 15-month-old daughter by abandoning her to the rising tide on a beach in northern France. But as the trial continues, her own family history, doubts, and fears about motherhood are steadily dislodged as the life story of the accused is gradually revealed.
A75: Chevalier | D75: 1 | E75: Hulu | F75: 6.5 | G75: Music & Musical, Drama, History | H75: Based on factual story of composer Joseph Bologne, Chevalier de Saint-Georges, the illegitimate son of an African enslaved and a French plantation owner, who rises to heights in French society as a composer before an ill-fated love affair.
A76: Infinity Pool | D76: 1 | E76: Hulu | F76: 6 | G76: Horror, Science-Fiction, Mystery & Thriller, Crime | H76: A wealthy young couple is on a luxurious beach holiday when they meet an odd but compelling stranger. Moved to follow her outside of their resort the pair are suddenly faced with a culture of shocking violence and hedonism. Beyond the safety of their hotel gates, the two are seduced to partake in the deadly decadence of island life. When a tragic accident occurs the pair are forced to make unimaginable choices with horrifying consequences.
A77: White Men Can't Jump | D77: 1 | E77: Hulu | F77: 5.1 | G77: Drama, Comedy, Sport | H77: Cash-strapped and in need of extra funds, a pair of street ballers take to the court to get their hustle on. Originally set on conning each other, the duo reconciles their differences and team up to swindle their unwitting opponents. Standing on either side of a cultural divide, the two individuals are brought together by their ability to play and their desire to earn a quick buck.
A78: Fool's Paradise | D78: 1 | E78: Hulu | F78: 4.7 | G78: Comedy | H78: A down-on-his-luck publicist discovers a recently released mental health patient who looks just like a misbehaving movie star. The publicist subs him into a film, creating a new star. But fame and fortune are not all they are cracked up to be.
A79: The Wonderful Story of Henry Sugar | D79: 1 | E79: Netflix | F79: 7.4 | G79: Comedy, Drama, Action & Adventure, Fantasy | H79: Henry Sugar is a man who learns to see through objects and predict the future. He must learn what it means to be responsible when wielding his newfound powers. He runs in and out of trouble and dons all manner of disguises in an attempt to use his power for good. Alongside the story of Henry Sugar, this anthology of stories brings to life a selection of stories that also includes autobiographical works about the author Roald Dahl himself.
A80: Nyad | D80: 1 | E80: Netflix | F80: 7.1 | G80: Drama, Sport | H80: At 64 years old, Diana Nyad the marathon swimmer takes on her most ambitious challenge yet. Swimming from Cuba to Florida without a shark cage is not only a test of her endurance and willpower but also of her bravery. The 110-mile-long route is across open water and she needs the support of her two trusted companions. Bonnie Stoll, her swimming coach, and John Bartlett, the navigator of her path are both on hand to help. Still, the task is neither simple nor easy. The 53-hour swim will push Diana to her absolute limit and the danger of the sea is ever-present.
A81: Big George Foreman | D81: 1 | E81: Netflix | F81: 6.6 | G81: Drama, History, Sport | H81: Fuelled by his love of family and community, George Foreman grew up poor with boxing as his only outlet. After winning an Olympic Gold and then the World Heavyweight title, Foreman was on top of the world until a near-death experience left him a changed man. Finding his faith, he retired from a successful boxing career in order to become a preacher. But when times got tough for his family and church, his calling called him back. George stepped back again into the ring again at the age of 45, seeking to become the oldest heavyweight champion in boxing history.
A82: Rebel Moon – Part One: A Child of Fire | D82: 1 | E82: Netflix | F82: 6.3 | G82: Drama, Fantasy, Science-Fiction, Action & Adventure | H82: Balisarius is a tyrannical despot in control of huge armies that threaten a peaceful colony on the very edge of the galaxy. The people of Veldt send off an emissary with a mysterious past to seek out protectors and helpers against the oncoming threat. With warriors from neighbouring planets rising to the call of resistance against tyranny and readying themselves to face the villainous Balisarius an epic battle is set that will define the course of the galaxy.
A83: Old Dads | D83: 1 | E83: Netflix | F83: 6.2 | G83: Comedy | H83: A cranky middle-aged dad and his two best friends find themselves out of step in a changing world of millennial CEOs and powerful preschool principals.
A84: The Pope's Exorcist | D84: 1 | E84: Netflix | F84: 6.1 | G84: Horror, Mystery & Thriller | H84: Father Gabriele Amorth has had a strange and mysterious occupation throughout his life. Deep inside the Vatican, beneath labyrinthine hallways decked in opulence, this Catholic priest has been practicing a dark art. Under the guidance of the Pope, the Church is battling the dangerous possessive power of Satan. On a mission to deliver the righteous from the throes of evil, this is the story of Father Gabriele Amorth. In the church's ongoing fight against evil, Father Amorth is the chief exorcist. This real-life figure performed over 100,000 exorcisms from World War II through to the internet age.
A85: 65 | D85: 1 | E85: Netflix | F85: 5.4 | G85: Science-Fiction, Action & Adventure, Drama, Mystery & Thriller | H85: An emergency landing brings an astronaut to a mysterious planet. He spends his time desperately trying to figure out how to leave with the only other survivor a young girl who needs his protection. Mills and Koa explore the uncanny planet that feels at once familiar and odd. Quickly the pair discover that their fellow inhabitants are ancient dinosaurs and that the planet is Earth, 65 million years in the past. All they can do is try to survive being hunted until they can escape.
A86: Society of the Snow | D86: 1 | E86: Netflix
A87: Memory | D87: 1 | E87: Paramount
A88: 80 for Brady | D88: 1 | E88: Prime | F88: 5.8 | G88: Comedy, Drama, Sport | H88: A quartet of elderly best friends decide to live life to the fullest by taking a wild trip to the Super Bowl LI to see their hero Tom Brady play.
A89: Godzilla Minus One | D89: 1 | F89: 8.5 | G89: Science-Fiction, Horror, Action & Adventure, Drama | H89: In postwar Japan, a new terror rises. Will the devastated people be able to survive... let alone fight back?
A90: Taylor Swift's Eras Tour | D90: 1 | F90: 8.3 | G90: Music & Musical, Documentary | H90: The Eras Tour is the sixth major headlining concert from multi-award-winning singer-songwriter Taylor Swift. But this tour is unlike anything that has come before. Performances on the tour last over three hours and feature music from the different eras of Taylor Swift’s career. Each show is split into ten different acts that represent one of her ten studio albums. The documentary movie covers shows across five continents and touches on the fan frenzy around the release of the tour tickets. Get a front-row seat for the show and a backstage pass to behind-the-scenes interviews with Taylor Swift.
A91: Anatomy of a Fall | D91: 1 | F91: 7.9 | G91: Drama, Mystery & Thriller, Crime | H91: A woman is suspected of her husband’s murder, and their blind son faces a moral dilemma as the sole witness.
A92: Joyland | D92: 1 | F92: 7.6 | G92: Drama, Romance | H92: As a patriarchal family yearn for the birth of a baby boy to continue their family line, their youngest son secretly joins an erotic dance theatre and falls for a transgender starlet.
A93: BlackBerry | D93: 1 | F93: 7.4 | G93: Comedy, Drama, History | H93: Mike Lazaridis and Douglas ‘Doug’ Fregin are friends developing a groundbreaking idea: putting e-mail capabilities into a mobile phone. The concept would be the winning idea of the early 2000s and revolutionize the budding tech industry. But before the meteoric rise of the company and its flagship product, the BlackBerry smartphone, the business needed a shot in the arm from cutthroat capitalist Jim Balsillie. As sales soared and the business thrived, the people behind the product grew isolated by their success and the multimillion-dollar empire began to crumble.
A94: Are You There God? It's Me, Margaret | D94: 1 | F94: 7.4 | G94: Drama, Comedy, Kids & Family | H94: Margaret Simon is an inquisitive eleven-year-old. With her parents, she is moving to the New Jersey suburbs from the bustle of New York City. With one parent a Christian and the other following the Jewish faith, Margaret finds herself spiritually caught and continuously curious. Experiencing the growing pains and power of adolescence, the young teen is navigating a slippery relationship with God. Raised without a single religious affiliation, the teen reaches for support in the many ways she knows how while undergoing the problems and challenges of puberty.
A95: Gran Turismo | D95: 1 | F95: 7.2 | G95: Drama, Sport, Action & Adventure | H95: Jann Mardenborough is an avid gamer who loves Gran Turismo more than any other game in his collection. When Nissan hosts a video game competition, Jann enters in the hopes of winning the chance to train and become a professional race car driver in real life. But in order to make the transition from the screen to the track, Jann must heed the advice of Jack Salter, his trainer who won’t hide his skepticism.
A96: Beau is Afraid | C96: 1 | D96: 1 | F96: 6.8 | G96: Horror, Comedy, Drama, Action & Adventure, Fantasy | H96: Set in an alternative present and spanning four generations, Beau is Afraid tells the story of an anxious but amiable man on an epic journey. Riddled with paranoia and anxiety, Beau is desperately trying to hurry home to see his mother. Beset with the physical manifestation of his greatest fears, Beau’s travel becomes his greatest test.
A97: They Shot the Piano Player | D97: 1 | F97: 6.8 | G97: Animation, Drama, History | H97: New York, 2010. Jeff Harris, a music journalist, sets out to uncover the truth about Francisco Tenório Júnior, a young Brazilian samba-jazz pianist who disappeared in Buenos Aires on March 18, 1976.
A98: Next Goal Wins | D98: 1 | F98: 6.5 | G98: Comedy, Drama, Sport | H98: Thomas Rongen is a soccer coach who loves the beautiful game. But when he’s offered the job of coaching the American Samoa national team, he knows it will be an almost impossible task. The country is known as the worst team in the soccer world rankings. As the World Cup qualifiers approach, Rongen must find and develop a team that can compete. With the arrival of fa’afafine player Jaiyah Saelua, the team made history by including the first transgender player to play in a World Cup game.
A99: Corner Office | C99: 1 | D99: 1 | F99: 6 | G99: Comedy, Drama | H99: In this office satire, Orson, a straight-laced employee, retreats to a blissfully empty corner office to get away from his lackluster colleagues. But why does this seem to upset them so much?
A100: The Color Purple | C100: 1 | D100: 1
A101: Still: A Michael J. Fox Movie | E101: Apple | F101: 8.1 | G101: Documentary | H101: Follows the life of beloved actor and advocate Michael J. Fox, exploring his personal and professional triumphs and travails, and what happens when an incurable optimist confronts an incurable disease.
A102: Stephen Curry: Underrated | E102: Apple | F102: 7.3 | G102: Documentary, Sport | H102: Stephen Curry is one of the greatest basketball players of all time. But from a young age, the master of the three-pointer has always been underrated and overlooked. This documentary tracks his progress from a teenager who was considered to be too small to play professional basketball all the way to winning the NBA Finals MVP Award. Featuring tell-all interviews with family and friends, Stephen Curry: Underrated is the story of the unlikeliest basketball icon the world has ever seen.
A103: Flora and Son | E103: Apple | F103: 7 | G103: Comedy, Drama, Music & Musical, Romance | H103: Single mom Flora is at a loss about what to do with her rebellious teenage son, Max. Her efforts to keep him out of trouble lead to a beat-up acoustic guitar, a washed-up LA musician, and harmony for this frayed Dublin family.
A104: The Pigeon Tunnel | E104: Apple | F104: 7 | G104: Documentary | H104: Spans six decades as le Carré gives his final and most personal interview, interrupted with rare archival footage and dramatic anecdotes. It is set against the stormy Cold War backdrop that extends into the present day.
A105: Sharper | E105: Apple | F105: 6.7 | G105: Crime, Drama, Mystery & Thriller | H105: Sharper is a comedy thriller by the award-winning filmmaker Benjamin Caron. Produced by A24 and distributed by Apple Studios, Sharper showcases how naive and weak the wealthiest in society truly is. Set in the cesspit of New York City where the scramble for wealth leaves so many in the gutters, Madeline and Max are out to get rich and then get out. Mixing in the milieu of billionaires, the pair know that the only way to turn a profit from their performed position amongst the elite is to steal from everyone around them. Whether the rich know it or not, the con is very much on.
A106: The Beanie Bubble | E106: Apple | F106: 6.3 | G106: Drama, Comedy | H106: Ty Warner was a hapless toy salesman looking to make a quick buck until he met three brilliant women. Ty is credited with turning simple stuffed animals into a cultural phenomenon that captured the imagination of children and adults across the nation. But this is not just the story of a ruthless businessman, it’s about the unsung heroes behind the beanie baby craze.
A107: Fingernails | E107: Apple | F107: 5.9 | G107: Romance, Science-Fiction, Drama | H107: Anna and Ryan have found true love together. It’s been proven by a controversial test. There’s just one problem: Anna still isn’t sure. Then she meets Amir.
A108: Ghosted | E108: Apple | F108: 5.8 | G108: Action & Adventure, Comedy, Romance | H108: After a first date, Cole Riggan thinks he might have found love. But when Sadie ghosts his many text messages he decides that he’ll pursue her with a grand romantic gesture. Knowing that she’s traveled to London for work, Cole throws caution to the wind and seeks her out. What he finds is an international conspiracy and himself in the middle of it. Sadie is a CIA spy who alongside her various missions now has to protect her unwitting love interest who’s mixed up in the madness.
A109: Bobi Wine: The People's President | E109: Disney | F109: 7.7 | G109: Documentary | H109: Uganda has one the youngest populations in the world and one of its most flagrantly anti-democratic governments. These are ingredients for revolution, and Bobi Wine and his wife Barbie Kyagulanyi are stirring the pot. When the charismatic Bobi, a musician and member of parliament, announces his campaign for president, Uganda’s youth are ecstatic, filling parks and streets for every speech, and singing Bobi’s anthems of peace and freedom. But then comes the crackdown, orchestrated by Yoweri Museveni, a brutal dictator who has ruled Uganda for 36 years. Bobi and his crew survive arrests, beatings, torture, riots and raids.
A110: Wild Life | E110: Disney | F110: 7.1 | G110: Documentary | H110: From Oscar-winning filmmakers Chai Vasarhelyi and Jimmy Chin, "Wild Life" follows conservationist Kris Tompkins on an epic, decades-spanning love story as wild as the landscapes she dedicated her life to protecting. After falling in love in mid-life, Kris and the outdoorsman and entrepreneur Doug Tompkins left behind the world of the massively successful outdoor brands they'd helped pioneer like Patagonia, The North Face, and Esprit, and turned their attention to a visionary effort to create National Parks throughout Chile and Argentina. "Wild Life" chronicles the highs and lows of their journey to effect the largest private land donation in history.
A111: Stan Lee | E111: Disney | F111: 6.9 | G111: Documentary | H111: Celebrate the legacy of Stan Lee as the co-creator of such legendary characters as Fantastic Four, Iron Man, the X-Men, The Avengers, and hundreds more.
A112: The Mission | E112: Disney | F112: 6.5 | G112: Documentary | H112: 26-year-old American missionary John Chau was killed as he attempted to make contact with an Indigenous group off the coast of India, one of the last communities on the planet still living in isolation.
... A148: Miguel Wants to Fight | E148: Hulu | F148: 5.7 | G148: Comedy | H148: A coming of age comedy about a 17-year-old in who asks his three best friends to help him get in his first fight ever before he moves to a new city.
A149: The Old Way | C149: 1 | E149: Hulu | F149: 5.5 | G149: Western, Action & Adventure, Drama | H149: An old gunslinger and his daughter must face the consequences of his past, when the son of a man he murdered years ago arrives to take his revenge.
A150: Door Mouse | E150: Hulu | F150: 5.5 | G150: Mystery & Thriller, Drama | H150: A burlesque dancer with dreams of becoming a comic book artist investigates the disappearance of a close friend.
A151: Monster Inside | E151: Hulu | F151: 5.5 | G151: Horror, Documentary, Crime | H151: Russ McKamey is the creator of the world's "most extreme haunted house" - McKamey Manor. He is also a manipulative abuser, according to three people who realize the horror is never over once you decide to enter the Manor. Russ McKamey is the creator of the world's "most extreme haunted house" - McKamey Manor. He is also a manipulative abuser, according to three people who realize the horror is never over once you decide to enter the Manor.
A152: Space Oddity | E152: Hulu | F152: 5.4 | G152: Comedy, Romance, Science-Fiction, Drama | H152: A space-obsessed man gets the opportunity of a lifetime thanks to a Mars colonization program but finds his plans compromised by his feelings for a woman who brings him down to Earth.
A153: One True Loves | E153: Hulu | F153: 5.4 | G153: Drama, Comedy, Romance | H153: Emma and Jesse are living the perfect life together, until Jesse disappears in a tragic helicopter crash on their first wedding anniversary. Four years later, Emma has found happiness again and is about to marry her best friend when Jesse resurfaces, turning her world upside down and leaving her torn between two great loves.
A154: Aporia | E154: Hulu | F154: 5.4 | G154: Drama, Science-Fiction | H154: Since losing her husband, Sophie has struggled to manage grief, a full-time job, and parenting her devastated daughter, but when a former physicist reveals a secret time-bending machine, Sophie will be faced with an impossible choice.
...

Sheet 2022
B1: Seen | C1: Own | D1: Want to see | E1: Where | F1: IMDb | G1: =SUM(B:B) -> 74 | H1: =_xlfn.CONCAT(SUM(C:C)," (",SUMPRODUCT(C:C,--(NOT(B:B=1))),")") -> 48 (21)
A2: Jackass Forever | B2: 1 | C2: 1
A3: The Batman | B3: 1 | C3: 1
A4: Everything Everywhere All at Once | B4: 1 | C4: 1
A5: Fantastic Beasts: The Secrets of Dumbledore | B5: 1 | C5: 1
A6: The Bad Guys | B6: 1 | C6: 1
A7: The Northman | B7: 1 | C7: 1
A8: The Unbearable Weight of Massive Talent | B8: 1 | C8: 1
A9: The Bob's Burgers Movie | B9: 1 | C9: 1
A10: Top Gun: Maverick | B10: 1 | C10: 1
A11: Where the Crawdads Sing | B11: 1 | C11: 1
A12: Nope | B12: 1 | C12: 1
A13: DC League of Super-Pets | B13: 1 | C13: 1
... A28: Marcel the Shell with Shoes On | B28: 1 | C28: 1
A29: The 355 | B29: 1
A30: Moonfall | B30: 1
A31: Death on the Nile | B31: 1
A32: Marry Me | B32: 1
A33: Dog | B33: 1
A34: Uncharted | B34: 1
A35: Studio 666 | B35: 1
A36: The Adam Project | B36: 1
A37: The Outfit | B37: 1
A38: The Lost City | B38: 1
A39: Morbius | B39: 1
A40: Doctor Strange in the Multiverse of Madness | B40: 1
... A75: Ambulance | B75: 1
A76: Cyrano | C76: 1
A77: After Yang | C77: 1
A78: Sonic the Hedgehog 2 | C78: 1
A79: Fall | C79: 1
A80: Emily the Criminal | C80: 1
A81: Three Thousand Years of Longing | C81: 1
A82: Confess, Fletch | C82: 1
A83: Meet Cute | C83: 1
A84: The Good House | C84: 1
A85: Armageddon Time | C85: 1
A86: Poker Face | C86: 1
A87: Spoiler Alert | C87: 1
... A96: Smile | C96: 1
A97: Hotel Transylvania: Transformania | D97: 1
A98: The Worst Person in the World | D98: 1
A99: Pixar's Turning Red | D99: 1
A100: Downton Abbey: A New Era | D100: 1
A101: Speak No Evil | D101: 1
A102: The Greatest Beer Run Ever | D102: 1
A103: Aftersun | D103: 1
A104: ParaNorman | D104: 1
A105: Emancipation | D105: 1
A106: A Hero
A107: King Car
A108: See For Me
A109: Belle
A110: Scream
A111: A Cops and Robbers Story
A112: The Pink Cloud
A113: Shattered
A114: Who We Are: A Chronicle of Racism in America
A115: The King's Daughter
A116: Redeeming Love
A117: The Tiger Rising
... A549: Night at the Museum: Kahmunrah Rises Again

Sheet 2021
B1: Seen | C1: Own | D1: Want to see | E1: Where | F1: IMDb | G1: =SUM(B:B) -> 69 | H1: =_xlfn.CONCAT(SUM(C:C)," (",SUMPRODUCT(C:C,--(NOT(B:B=1))),")") -> 49 (15)
A2: Barb and Star Go to Vista Del Mar | B2: 1 | C2: 1
A3: Judas and the Black Messiah | B3: 1 | C3: 1
A4: Tom & Jerry | B4: 1 | C4: 1
A5: The Father | B5: 1 | C5: 1
A6: Zack Snyder's Justice League | B6: 1 | C6: 1
A7: The Courier | B7: 1 | C7: 1
A8: Nobody | B8: 1 | C8: 1
A9: Marvel's Black Widow | B9: 1 | C9: 1
A10: The Suicide Squad | B10: 1 | C10: 1
A11: Free Guy | B11: 1 | C11: 1
A12: Respect | B12: 1 | C12: 1
A13: The Protégé | B13: 1 | C13: 1
... A35: Spencer | B35: 1 | C35: 1
A36: The Dig | B36: 1
A37: Nomadland | B37: 1
A38: The United States vs. Billie Holiday | B38: 1
A39: Raya and the Last Dragon | B39: 1
A40: Godzilla vs. Kong | B40: 1
A41: The Woman in the Window | B41: 1
A42: Army of the Dead | B42: 1
A43: Cruella | B43: 1
A44: In the Heights | B44: 1
A45: Pixar's Luca | B45: 1
A46: No Sudden Move | B46: 1
A47: Space Jam: A New Legacy | B47: 1
... A70: The King's Man | B70: 1
A71: Boogie | C71: 1
A72: Pixie | C72: 1
A73: Together Together | C73: 1
A74: The Mitchells vs. the Machines | C74: 1
A75: Stillwater | C75: 1
A76: Malignant | C76: 1
A77: The Card Counter | C77: 1
A78: No Time To Die | C78: 1
A79: C'mon C'mon | C79: 1
A80: The Beatles: Get Back | C80: 1
A81: The Matrix Resurrections | C81: 1
A82: Last Looks | C82: 1
... A85: Don't Breathe 2 | C85: 1
A86: Derek DelGaudio's In & Of Itself | D86: 1
A87: Saint Maud | D87: 1
A88: French Exit | D88: 1
A89: I Care a Lot | D89: 1
A90: Cherry | D90: 1
A91: Coming 2 America | D91: 1
A92: Shiva Baby | D92: 1
A93: Spiral: From The Book of Saw | D93: 1
A94: Zola | D94: 1
A95: Gunpowder Milkshake | D95: 1
A96: Pig | D96: 1
A97: Cry Macho | D97: 1
... A112: Vacation Friends | D112: 1
A113: Shadow in the Cloud
A114: Pieces of a Woman
A115: The Reason I Jump
A116: Locked Down
A117: Acasa, My Home
A118: American Skin
A119: MLK/FBI
A120: Outside the Wire
A121: Some Kind of Heaven
A122: The Human Factor
A123: No Man's Land
A124: Notturno
... A466: Oslo

Sheet 2020
B1: Seen | C1: Own | D1: Want to see | E1: Where | F1: IMDb | G1: =SUM(B:B) -> 54 | H1: =_xlfn.CONCAT(SUM(C:C)," (",SUMPRODUCT(C:C,--(NOT(B:B=1))),")") -> 30 (11)
A2: Dolittle | B2: 1 | C2: 1
A3: The Gentlemen | B3: 1 | C3: 1
A4: Birds of Prey: And the Fantabulous Emancipation of One Harley Quinn | B4: 1 | C4: 1
A5: Sonic the Hedgehog | B5: 1 | C5: 1
A6: The Invisible Man | B6: 1 | C6: 1
A7: The Way Back | B7: 1 | C7: 1
A8: The Hunt | B8: 1 | C8: 1
A9: Scoob! | B9: 1 | C9: 1
A10: The King of Staten Island | B10: 1 | C10: 1
A11: Irresistible | B11: 1 | C11: 1
A12: Tenet | B12: 1 | C12: 1
A13: Antebellum | B13: 1 | C13: 1
... A20: Class Action Park | B20: 1 | C20: 1
A21: Like a Boss | B21: 1
A22: Horse Girl | B22: 1
A23: The Photograph | B23: 1
A24: Downhill | B24: 1
A25: Emma | B25: 1
A26: Pixar's Onward | B26: 1
A27: The Banker | B27: 1
A28: Lost Girls | B28: 1
A29: The Lovebirds | B29: 1
A30: The Vast of Night | B30: 1
A31: Shirley | B31: 1
A32: Da 5 Bloods | B32: 1
... A55: Songbird | B55: 1
A56: Bad Boys For Life | C56: 1
A57: The Rhythm Section | C57: 1
A58: The Jesus Rolls | C58: 1
A59: Bill & Ted Face the Music | C59: 1
A60: Mulan | C60: 1
A61: Kajillionaire | C61: 1
A62: Freaky | C62: 1
A63: Half Brothers | C63: 1
A64: Fatale | C64: 1
A65: The Outpost | C65: 1
A66: The Grudge
A67: Underwater
A68: Les Misérables
A69: Three Christs
A70: The Turning
A71: Color Out of Space
A72: The Last Full Measure
A73: Gretel and Hansel
A74: The Assistant
A75: Incitement
A76: The Traitor
A77: And Then We Danced
... A119: Robert the Bruce
A120: True History of the Kelly Gang | C120: 1
A121: To the Stars
A122: Arkansas
A123: Bull
A124: Capital in the Twenty-First Century
A125: Deerskin
A126: Endings, Beginnings
A127: The Half of It
A128: The Wretched
A129: How to Build a Girl
A130: Spaceship Earth
A131: Valley Girl
A132: Walkaway Joe
... A146: Here Awhile
A147: 7500
A148: Babyteeth
A149: Miss Juneteenth
A150: You Should Have Left
A151: Hamilton
A152: John Lewis: Good Trouble
A153: Relic
A154: The Truth
A155: Greyhound
A156: Sometimes Always Never
A157: Dirt Music
A158: Ghosts of War
A159: Human Capital
... A207: The Glorias
A208: 2067
A209: The Antenna
A210: A Call to Spy
A211: Death of Me
A212: Dick Johnson is Dead
A213: Possessor Uncut
A214: Save Yourselves!
A215: Hubie Halloween
A216: The War with Grandpa
A217: The Forty-Year-Old Version
A218: The Wolf of Snow Hollow
A219: Honest Thief
A220: Love and Monsters
... A346: Coastal Elites

Sheet 2019
B1: Seen | C1: Own | D1: Want to see | E1: Where | F1: IMDb | G1: =SUM(B:B) -> 76 | H1: =_xlfn.CONCAT(SUM(C:C)," (",SUMPRODUCT(C:C,--(NOT(B:B=1))),")") -> 64 (23)
A2: The Man Who Killed Hitler and Then The Bigfoot | B2: 1 | C2: 1
A3: Isn't It Romantic | B3: 1 | C3: 1
A4: Captain Marvel | B4: 1 | C4: 1
A5: Us | B5: 1 | C5: 1
A6: The Beach Bum | B6: 1 | C6: 1
A7: Dumbo | B7: 1 | C7: 1
A8: Shazam! | B8: 1 | C8: 1
A9: Marvel's Avengers: Endgame | B9: 1 | C9: 1
A10: Long Shot | B10: 1 | C10: 1
A11: The Hustle | B11: 1 | C11: 1
A12: John Wick: Chapter 3 - Parabellum | B12: 1 | C12: 1
A13: Booksmart | B13: 1 | C13: 1
... A40: Little Women | B40: 1 | C40: 1
A41: 1917 | B41: 1 | C41: 1
A42: Parasite | B42: 1 | C42: 1
A43: A Dog's Way Home | B43: 1
A44: Captive State | B44: 1
A45: The Highwaymen | B45: 1
A46: Extremely Wicked, Shockingly Evil, and Vile | B46: 1
A47: A Dog's Journey | B47: 1
A48: Photograph | B48: 1
A49: Aladdin | B49: 1
A50: Godzilla: King of Monsters | B50: 1
A51: The Secret Life of Pets 2 | B51: 1
A52: Late Night | B52: 1
A53: Men in Black: International | B53: 1
A54: The Art of Racing in the Rain | B54: 1
... A77: The Report | B77: 1
A78: The Upside | C78: 1
A79: Glass | C79: 1
A80: Fighting with My Family | C80: 1
A81: Missing Link | C81: 1
A82: Pokémon Detective Pikachu | C82: 1
A83: Brightburn | C83: 1
A84: Shaft | C84: 1
A85: The Dead Don't Die | C85: 1
A86: Anna | C86: 1
A87: Crawl | C87: 1
A88: Judy | C88: 1
A89: Motherless Brooklyn | C89: 1
... A99: Spies in Disguise | C99: 1
A100: Miss Bala | D100: 1
A101: Velvet Buzzsaw | D101: 1
A102: Cold Pursuit | D102: 1
A103: What Men Want | D103: 1
A104: Greta | D104: 1
A105: Saint Judy | D105: 1
A106: Gloria Bell | D106: 1
A107: Triple Frontier | D107: 1
A108: Hotel Mumbai | D108: 1
A109: Dragged Across Concrete | D109: 1
A110: High Life | D110: 1
A111: Hellboy | D111: 1
... A127: Dolemite is My Name | D127: 1
A128: Jay and Silent Bob Reboot | C128: 1 | D128: 1
A129: Zombieland: Double Tap | D129: 1
A130: The Current War | D130: 1
A131: Waves | D131: 1
A132: Dark Waters | D132: 1
A133: Portrait of a Lady on Fire | D133: 1
A134: Star Wars: The Rise of Skywalker | D134: 1
A135: Between Two Ferns: The Movie | D135: 1
A136: The Vanishing
A137: Replicas
A138: The Aspern Papers
A139: Sgt. Will Gardner
A140: The Heiresses
A141: An Acceptable Loss
A142: Adult Life Skills
A143: The Standoff at Sparrow Creek
A144: The Kid Who Would Be King
A145: Serenity
A146: In Like Flynn
A147: King of Thieves
... A337: A Beautiful Day in the Neighborhood
A338: 3022
A339: Citizen K
A340: Hala
A341: Shooting the Mafia
A342: The Aeronauts
A343: Playmobil: The Movie
A344: The Disappearance of My Mother
A345: Little Joe
A346: The Wolf Hour
A347: Black Christmas
A348: Cunningham
A349: A Hidden Life
A350: Seberg
... A404: Share

Sheet 2018
B1: Seen | C1: Own | D1: Want to see | E1: Where | F1: IMDb | G1: =SUM(B:B) -> 64 | H1: =_xlfn.CONCAT(SUM(C:C)," (",SUMPRODUCT(C:C,--(NOT(B:B=1))),")") -> 82 (34)
A2: Winchester | B2: 1 | C2: 1
A3: Widows | B3: 1 | C3: 1
A4: White Boy Rick | B4: 1 | C4: 1
A5: Venom | B5: 1 | C5: 1
A6: The Commuter | B6: 1 | C6: 1
A7: Spider-Man: Into the Spider-Verse | B7: 1 | C7: 1
A8: Smallfoot | B8: 1 | C8: 1
A9: Skyscraper | B9: 1 | C9: 1
A10: Searching | B10: 1 | C10: 1
A11: Red Sparrow | B11: 1 | C11: 1
A12: Rampage | B12: 1 | C12: 1
A13: Ocean's 8 | B13: 1 | C13: 1
... A47: Leave No Trace | B47: 1 | C47: 2
A48: Welcome to Marwen | B48: 1
A49: Vice | B49: 1
A50: The Spy Who Dumped Me | B50: 1
A51: The Meg | B51: 1
A52: The King | B52: 1
A53: The Happytime Murders | B53: 1
A54: The Favourite | B54: 1
A55: The Ballad of Buster Scruggs | B55: 1
A56: Sorry to Bother You | B56: 1
A57: Operation Finale | B57: 1
A58: Love, Simon | B58: 1
A59: Jurassic World: Fallen Kingdom | B59: 1
... A65: Adrift | B65: 1
A66: Christopher Robin | C66: 1
A67: The Wife | C67: 1
A68: The Sisters Brothers | C68: 1
A69: The Mule | C69: 1
A70: The Hate U Give | C70: 1
A71: The Front Runner | C71: 1
A72: The Catcher Was a Spy | C72: 1
A73: The 15:17 to Paris | C73: 1
A74: Terminal | C74: 1
A75: Super Troopers 2 | C75: 1
A76: Sicario: Day of the Soldado | C76: 1
A77: Ready Player One | C77: 1
... A98: Borg vs McEnroe | C98: 1
A99: You Were Never Really Here | D99: 1
A100: Won't You Be My Neighbor? | D100: 1
A101: Vox Lux | D101: 1
A102: Upgrade | D102: 1
A103: Tully | D103: 1
A104: Thoroughbreds | D104: 1
A105: The Possession of Hannah Grace | D105: 1
A106: The Old Man & The Gun | D106: 1
A107: The Oath | D107: 1
A108: The Nutcracker and the Four Realms | D108: 1
A109: The Miseducation of Cameron Post | D109: 1
A110: The House with a Clock in its Walls | D110: 1
... A148: 22 July | D148: 1
A149: Zoe
A150: Woman Walks Ahead
A151: Wildlife
A152: Whitney
A153: Where is Kyra?
A154: Where Hands Touch
A155: When We First Met
A156: What They Had
A157: Westwood: Punk, Icon, Activist
A158: Western
A159: We the Animals
A160: Viper Club
... A379: Destination Wedding
A380: Den of Thieves | C380: 1
A381: Death Wish
A382: Dear Dictator
A383: Dark River
A384: Dark Crimes
A385: Damsel
A386: Damascus Cover
A387: Come Sunday
A388: Cold War
A389: Clara's Ghost
A390: Claire's Camera
A391: Chef Flynn
A392: Cargo
... A439: 6 Balloons

Sheet 2017
B1: Seen | C1: Own | D1: Want to see | E1: Where | F1: IMDb | G1: =SUM(B:B) -> 53 | H1: =_xlfn.CONCAT(SUM(C:C)," (",SUMPRODUCT(C:C,--(NOT(B:B=1))),")") -> 77 (29)
A2: A Dog's Purpose | B2: 1 | C2: 1
A3: John Wick: Chapter Two | B3: 1 | C3: 1
A4: The LEGO Batman Movie | B4: 1 | C4: 1
A5: Get Out | B5: 1 | C5: 1
A6: Kong: Skull Island | B6: 1 | C6: 1
A7: The Boss Baby | B7: 1 | C7: 1
A8: Buster's Mal Heart | B8: 1 | C8: 1
A9: Snatched | B9: 1 | C9: 1
A10: Baywatch | B10: 1 | C10: 1
A11: Pirates of the Caribbean: Dead Men Tell No Tales | B11: 1 | C11: 1
A12: The Mummy | B12: 1 | C12: 1
A13: 47 Meters Down | B13: 1 | C13: 1
... A48: Justice League | B48: 1 | C48: 1
A49: Guardians of the Galaxy Vol. 2 | B49: 1
A50: Kingsman: The Golden Circle | B50: 1
A51: Marshall | B51: 1
A52: The Post | B52: 1
A53: War Machine | B53: 1
A54: Logan | C54: 1
A55: Beauty and the Beast | C55: 1
A56: CHIPS | C56: 1
A57: The Zookeeper's Wife | C57: 1
A58: Going in Style | C58: 1
A59: The Lost City of Z | C59: 1
A60: King Arthur: Legend of the Sword | C60: 1
A61: Alien: Covenant | C61: 1
A62: All Eyez on Me | C62: 1
A63: The Big Sick | C63: 1
A64: Detroit | C64: 1
A65: Blade Runner 2049 | C65: 1
... A78: Brawl in Cell Block 99 | C78: 1
A79: Jungle | B79: 1 | C79: 1
A80: The Founder | C80: 1
A81: Life | C81: 1
A82: The Beguiled | C82: 1
A83: Victoria & Abdul | C83: 1
A84: Split | D84: 1
A85: Rings | D85: 1
A86: The Comedian | D86: 1
A87: I Am Not Your Negro | D87: 1
A88: Fist Fight | D88: 1
A89: The Great Wall | D89: 1
A90: The Shack | D90: 1
A91: The Belko Experiment | D91: 1
A92: T2: Trainspotting | D92: 1
A93: Aftermath | D93: 1
A94: How to Be a Latin Lover | D94: 1
A95: Sleight | D95: 1
... A99: My Cousin Rachel | D99: 1
A100: 0.098611111 | D100: 1
A101: War for the Planet of the Apes | D101: 1
A102: Girls Trip | D102: 1
A103: Brigsby Bear | D103: 1
A104: The Dark Tower | D104: 1
A105: Ingrid Goes West | D105: 1
A106: Logan Lucky | D106: 1
A107: Patti Cake$ | D107: 1
A108: Birth of the Dragon | D108: 1
A109: Goon: Last of the Enforcers | D109: 1
A110: mother! | D110: 1
A111: Brad's Status | D111: 1
A112: The Meyerowitz Stories | D112: 1
... A129: The Immortal Life of Henrietta Lacks | D129: 1
A130: Underworld: Blood Wars
A131: Railroad Tigers
A132: The Bye Bye Man
A133: Monster Trucks
A134: Sleepless
A135: Alone in Berlin
A136: The Book of Love
A137: The Crash
A138: Go North
A139: xXx: The Return of Xander Cage
A140: Detour
A141: The Red Turtle
... A398: Tour de Pharmacy

Sheet 2016
B1: Seen | C1: Own | D1: Want to see | E1: Where | F1: IMDb | G1: =SUM(B:B) -> 35 | H1: =_xlfn.CONCAT(SUM(C:C)," (",SUMPRODUCT(C:C,--(NOT(B:B=1))),")") -> 65 (30)
A2: Deadpool | B2: 1 | C2: 1
A3: Race | B3: 1 | C3: 1
A4: Batman v Superman: Dawn of Justice | B4: 1 | C4: 1
A5: The Boss | B5: 1 | C5: 1
A6: Captain America: Civil War | B6: 1 | C6: 1
A7: Neighbors 2: Sorority Rising | B7: 1 | C7: 1
A8: The Nice Guys | B8: 1 | C8: 1
A9: Popstar: Never Stop Never Stopping | B9: 1 | C9: 1
A10: Now You See Me 2 | B10: 1 | C10: 1
A11: Pixar's Finding Dory | B11: 1 | C11: 1
A12: The Shallows | B12: 1 | C12: 1
A13: The Legend of Tarzan | B13: 1 | C13: 1
... A36: Free State of Jones | B36: 1 | C36: 1
A37: The 5th Wave | C37: 1
A38: Dirty Grandpa | C38: 1
A39: Hail, Caesar! | C39: 1
A40: Zoolander 2 | C40: 1
A41: Eddie the Eagle | C41: 1
A42: The Jungle Book | C42: 1
A43: X-Men: Apocalypse | C43: 1
A44: Me Before You | C44: 1
A45: Central Intelligence | C45: 1
A46: Don't Think Twice | C46: 1
A47: The Light Between Oceans | C47: 1
A48: Sully | C48: 1
... A66: Hidden Figures | C66: 1
A67: Kung Fu Panda 3 | D67: 1
A68: The Witch | D68: 1
A69: London Has Fallen | D69: 1
A70: Whiskey Tango Foxtrot | D70: 1
A71: Zootopia | D71: 1
A72: The Brothers Grimsby | D72: 1
A73: The Lobster | D73: 1
A74: The Divergent Series: Allegiant | D74: 1
A75: The Bronze | D75: 1
A76: Everybody Wants Some!! | D76: 1
A77: Elvis & Nixon | D77: 1
A78: The Huntsman: Winter's War | D78: 1
... A111: The Do-Over | D111: 1
A112: The Forest
A113: 13 Hours: The Secret Soldiers of Benghazi
A114: Norm of the North
A115: Ride Along 2
A116: The Boy
A117: Ip Man 3
A118: Mojave
A119: Synchronicity
A120: The Finest Hours
A121: Jane Got a Gun
A122: The Choice
A123: Pride and Prejudice and Zombies
... A291: Ouija: Origin of Evil
A292: 31
A293: Christine
A294: In a Valley of Violence
A295: Inferno
A296: Gimme Danger
A297: The Eagle Huntress
A298: The Ivory Game
A299: Almost Christmas
A300: Billy Lynn's Long Halftime Walk
A301: Shut In
A302: Elle
A303: The Love Witch
A304: The Monster
... A343: All the Way

Sheet 2015
B1: Seen | C1: Own | D1: Want to see | E1: Where | F1: IMDb | G1: =SUM(B:B) -> 26 | H1: =_xlfn.CONCAT(SUM(C:C)," (",SUMPRODUCT(C:C,--(NOT(B:B=1))),")") -> 47 (24)
A2: What We Do in the Shadows | B2: 1 | C2: 1
A3: Get Hard | B3: 1 | C3: 1
A4: Ex Machina | B4: 1 | C4: 1
A5: Avengers: Age of Ultron | B5: 1 | C5: 1
A6: San Andreas | B6: 1 | C6: 1
A7: Spy | B7: 1 | C7: 1
A8: Jurassic World | B8: 1 | C8: 1
A9: Minions | B9: 1 | C9: 1
A10: Ant-Man | B10: 1 | C10: 1
A11: Trainwreck | B11: 1 | C11: 1
A12: Southpaw | B12: 1 | C12: 1
A13: Black Mass | B13: 1 | C13: 1
... A24: Point Break | B24: 1 | C24: 1
A25: Vacation | B25: 1 | D25: 1
A26: Vice | B26: 1
A27: Hot Pursuit | B27: 1
A28: Home | C28: 1
A29: Mad Max: Fury Road | C29: 1
A30: Pitch Perfect 2 | C30: 1
A31: Aloha | C31: 1
A32: Max | C32: 1
A33: Ted 2 | C33: 1
A34: Terminator: Genisys | C34: 1
A35: The Stanford Prison Experiment | C35: 1
A36: Mission: Impossible - Rogue Nation | C36: 1
A37: Everest | C37: 1
A38: Hotel Transylvania 2 | C38: 1
A39: Room | C39: 1
... A51: Where to Invade Next | C51: 1
A52: Paddington | D52: 1
A53: Hot Tub Time Machine 2 | D53: 1
A54: Chappie | D54: 1
A55: Cinderella | D55: 1
A56: The Cobbler | D56: 1
A57: Divergent Series: Insurgent | D57: 1
A58: Entourage | D58: 1
A59: Me and Earl and the Dying Girl | D59: 1
A60: Dope | D60: 1
A61: The Man From U.N.C.L.E. | D61: 1
A62: American Ultra | D62: 1
A63: Pan | D63: 1
... A80: The Ridiculous 6 | D80: 1
A81: The Woman in Black 2: Angel of Death
A82: REC 4: Apocalypse
A83: Taken 3
A84: Predestination
A85: Blackhat
A86: The Wedding Ringer
A87: The Boy Next Door
A88: Mortdecai
A89: Strange Magic
A90: Black Sea
A91: The Duke of Burgundy
A92: Mommy
... A286: The Leisure Class

Sheet 2014
B1: Seen | C1: Own | D1: Want to see | E1: Where | F1: IMDb | G1: =SUM(B:B) -> 16 | H1: =_xlfn.CONCAT(SUM(C:C)," (",SUMPRODUCT(C:C,--(NOT(B:B=1))),")") -> 39 (25)
A2: The LEGO Movie | B2: 1 | C2: 1
A3: Captain America: The Winter Soldier | B3: 1 | C3: 1
A4: Neighbors | B4: 1 | C4: 1
A5: Godzilla | B5: 1 | C5: 1
A6: Sex Tape | B6: 1 | C6: 1
A7: Guardians of the Galaxy | B7: 1 | C7: 1
A8: Gone Girl | B8: 1 | C8: 1
A9: The Judge | B9: 1 | C9: 1
A10: John Wick | B10: 1 | C10: 1
A11: Interstellar | B11: 1 | C11: 1
A12: The Hunger Games: Mockingjay Part 1 | B12: 1 | C12: 1
A13: The Imitation Game | B13: 1 | C13: 1
... A15: Horrible Bosses 2 | B15: 1 | C15: 1
A16: Tammy | B16: 1
A17: Lucy | B17: 1
A18: That Awkward Moment | C18: 1
A19: 300: Rise of an Empire | C19: 1
A20: The Grand Budapest Hotel | C20: 1
A21: Draft Day | C21: 1
A22: Rio 2 | C22: 1
A23: X-Men: Days of Future Past | C23: 1
A24: Dawn of the Planet of the Apes | C24: 1
A25: Let's Be Cops | C25: 1
A26: The Equalizer | C26: 1
A27: St. Vincent | C27: 1
A28: Whiplash | C28: 1
A29: Birdman | C29: 1
... A42: The Gambler | C42: 1
A43: Jack Ryan: Shadow Recruit | D43: 1
A44: I, Frankenstein | D44: 1
A45: RoboCop | D45: 1
A46: Mr. Peabody & Sherman | D46: 1
A47: Veronica Mars | D47: 1
A48: Divergent | D48: 1
A49: Muppets Most Wanted | D49: 1
A50: Chef | D50: 1
A51: Million Dollar Arm | D51: 1
A52: Maleficent | D52: 1
A53: A Million Ways to Die in the West | D53: 1
A54: Obvious Child | D54: 1
... A69: American Sniper | D69: 1
A70: Paranormal Activity: The Marked Ones
A71: Beyond Outrage
A72: The Legend of Hercules
A73: Devil's Due
A74: The Nut Job
A75: Ride Along
A76: Like Father, Like Son
A77: Gimme Shelter
A78: Gloria
A79: Best Night Ever
A80: Tim's Vermeer
A81: The Monuments Men
... A273: The Normal Heart

Sheet 2013
B1: Seen | C1: Own | D1: Want to see | E1: Where | F1: IMDb | G1: =SUM(B:B) -> 15 | H1: =_xlfn.CONCAT(SUM(C:C)," (",SUMPRODUCT(C:C,--(NOT(B:B=1))),")") -> 41 (29) | I1: Wikipedia
A2: 42 | B2: 1 | C2: 1
A3: Iron Man 3 | B3: 1 | C3: 1
A4: Now You See Me | B4: 1 | C4: 1
A5: The Internship | B5: 1 | C5: 1
A6: Despicable Me 2 | B6: 1 | C6: 1
A7: Kick-Ass 2 | B7: 1 | C7: 1
A8: 12 Years a Slave | B8: 1 | C8: 1
A9: Thor: The Dark World | B9: 1 | C9: 1
A10: The Hunger Games: Catching Fire | B10: 1 | C10: 1
A11: Anchorman 2: The Legend Continues | B11: 1 | C11: 1
A12: The Wolf of Wall Street | B12: 1 | C12: 1
A13: In a World | B13: 1 | C13: 1
A14: Monsters University | B14: 1
A15: Delivery Man | B15: 1
A16: Frozen | B16: 1
A17: A Good Day to Die Hard | C17: 1
A18: The Incredible Burt Wonderstone | C18: 1
A19: Mud | C19: 1
A20: The Great Gatsby | C20: 1
A21: This Is the End | C21: 1
A22: Man of Steel | C22: 1
A23: The Heat | C23: 1
A24: White House Down | C24: 1
A25: Bad Words | C25: 1
A26: Blue Jasmine | C26: 1
A27: The Wolverine | C27: 1
A28: We're the Millers | C28: 1
... A45: The Butler | C45: 1
A46: John Dies at the End | D46: 1
A47: Spring Breakers | D47: 1
A48: Stoker | D48: 1
A49: The Croods | D49: 1
A50: Evil Dead | D50: 1
A51: The English Teacher | D51: 1
A52: Frances Ha | D52: 1
A53: Before Midnight | D53: 1
A54: World War Z | D54: 1
A55: Fruitvale Station | D55: 1
A56: Pacific Rim | D56: 1
A57: R.I.P.D. | D57: 1
... A69: The Secret Life of Walter Mitty | D69: 1
A70: Phil Spector
A71: Mary and Martha
A72: Behind the Candelabra
A73: Clear History
A74: Muhammad Ali's Greatest Fight
A75: 21 & Over
A76: A Dark Truth
A77: A Glimpse Inside the Mind of Charles Swan III
A78: A Haunted House
A79: Admission
A80: Beautiful Creatures
A81: Bless Me, Ultima
... A203: Metallica: Through the Never
A204: 1
A205: Grace Unplugged
A206: Runner Runner
A207: Machete Kills
A208: Escape Plan
A209: The Fifth Estate
A210: I'm in Love with a Church Girl
A211: The Counselor
A212: About Time
A213: Ender's Game
A214: Free Birds
A215: Last Vegas
A216: The Best Man Holiday
... A230: Labor Day

Sheet 2012
B1: Seen | C1: Own | D1: Want to see | E1: Where | F1: IMDb | G1: =SUM(B:B) -> 9 | H1: =_xlfn.CONCAT(SUM(C:C)," (",SUMPRODUCT(C:C,--(NOT(B:B=1))),")") -> 36 (28) | I1: Wikipedia
A2: The Hunger Games | B2: 1 | C2: 1
A3: The Avengers | B3: 1 | C3: 1
A4: Men in Black 3 | B4: 1 | C4: 1
A5: Argo | B5: 1 | C5: 1
A6: Django Unchained | B6: 1 | C6: 1
A7: The Dark Knight Rises | B7: 1 | C7: 1
A8: Silver Linings Playbook | B8: 1 | C8: 1
A9: The Bay | B9: 1 | C9: 1
A10: Wreck-It Ralph | B10: 1
A11: 21 Jump Street | C11: 1
A12: American Reunion | C12: 1
A13: Snow White and the Huntsman | C13: 1
A14: Prometheus | C14: 1
A15: Seeking a Friend for the End of the World | C15: 1
A16: Ted | C16: 1
A17: Ice Age: Continental Drift | C17: 1
A18: The Watch | C18: 1
A19: Total Recall | C19: 1
A20: The Campaign | C20: 1
A21: Trouble with the Curve | C21: 1
A22: Hotel Transylvania | C22: 1
... A38: Jack Reacher | C38: 1
A39: Casa de Mi Padre | D39: 1
A40: Jeff, Who Lives at Home | D40: 1
A41: Goon | D41: 1
A42: Moonrise Kingdom | D42: 1
A43: The Amazing Spider-Man | D43: 1
A44: The Bourne Legacy | D44: 1
A45: ParaNorman | D45: 1
A46: Anna Karenina | D46: 1
A47: The Perks of Being a Wallflower | D47: 1
A48: Frankenweenie | D48: 1
A49: Seven Psychopaths | D49: 1
A50: Sinister | D50: 1
... A52: Les Misérables | D52: 1
A53: The Devil Inside
A54: Beneath the Darkness
A55: Norwegian Wood
A56: Contraband
A57: Joyful Noise
A58: Albatross
A59: The Divide
A60: Don't Go in the Woods
A61: Sing Your Song
A62: Haywire
A63: Red Tails
A64: Underworld: Awakening
... A186: Diary of a Wimpy Kid: Dog Days
A187: 360
A188: Celeste and Jesse Forever
A189: Hope Springs
A190: 2 Days in New York
A191: The Odd Life of Timothy Green
A192: Ek Tha Tiger
A193: The Expendables 2
A194: Sparkle
A195: Compliance
A196: Cosmopolis
A197: Robot & Frank
A198: Community Service: The Movie
A199: Hit and Run
... A281: Promised Land

Sheet 2011
B1: Seen | C1: Own | D1: Want to see | E1: Where | F1: IMDb | G1: =SUM(B:B) -> 9 | H1: =_xlfn.CONCAT(SUM(C:C)," (",SUMPRODUCT(C:C,--(NOT(B:B=1))),")") -> 40 (31) | I1: Wikipedia
A2: The Green Hornet | B2: 1 | C2: 1
A3: Thor | B3: 1 | C3: 1
A4: Bridesmaids | B4: 1 | C4: 1
A5: Pirates of the Caribbean: On Stranger Tides | B5: 1 | C5: 1
A6: Green Lantern | B6: 1 | C6: 1
A7: Horrible Bosses | B7: 1 | C7: 1
A8: Harry Potter and the Deathly Hallows – Part 2 | B8: 1 | C8: 1
A9: Captain America: The First Avenger | B9: 1 | C9: 1
A10: Sherlock Holmes: A Game of Shadows | B10: 1 | C10: 1
A11: Just Go with It | C11: 1
A12: Take Me Home Tonight | C12: 1
A13: Soul Surfer | C13: 1
A14: Rio | C14: 1
A15: The Hangover Part II | C15: 1
A16: X-Men: First Class | C16: 1
A17: Friends with Benefits | C17: 1
A18: The Smurfs | C18: 1
A19: Rise of the Planet of the Apes | C19: 1
A20: The Help | C20: 1
A21: Moneyball | C21: 1
A22: J. Edgar | C22: 1
... A41: The Iron Lady | C41: 1
A42: Cedar Rapids | D42: 1
A43: Hall Pass | D43: 1
A44: The Lincoln Lawyer | D44: 1
A45: Paul | D45: 1
A46: Insidious | D46: 1
A47: Bad Teacher | D47: 1
A48: Warrior | D48: 1
A49: Drive | D49: 1
A50: Tinker Tailor Soldier Spy | D50: 1
A51: We Need to Talk About Kevin | D51: 1
A52: War Horse | D52: 1
A53: Phil Ochs: There but for Fortune
A54: Season of the Witch
A55: The Time That Remains
A56: Barney's Version
A57: The Dilemma
A58: No Strings Attached
A59: Open Season 3
A60: The Mechanic
A61: The Rite
A62: Cold Weather
A63: The Other Woman
A64: The Roommate
... A221: A Separation

Sheet 2010
B1: Seen | C1: Own | D1: Want to see | E1: Where | F1: IMDb | G1: =SUM(B:B) -> 0 | H1: =_xlfn.CONCAT(SUM(C:C)," (",SUMPRODUCT(C:C,--(NOT(B:B=1))),")") -> 0 (0) | I1: Wikipedia

Sheet Streaming
A2: Hulu | B2: =SUMPRODUCT('2023'!$F$1:$F$997,--('2023'!$E$1:$E$997=Streaming!$A2)/COUNTIF('2023'!$E$1:$E$997,Streaming!$A2)) -> 5.7405405 | C2: =COUNTIF('2023'!$E$1:$E$997,Streaming!$A2) -> 74
A3: Netflix | B3: =SUMPRODUCT('2023'!$F$1:$F$997,--('2023'!$E$1:$E$997=Streaming!$A3)/COUNTIF('2023'!$E$1:$E$997,Streaming!$A3)) -> 6.0595238 | C3: =COUNTIF('2023'!$E$1:$E$997,Streaming!$A3) -> 84
A4: Max | B4: =SUMPRODUCT('2023'!$F$1:$F$997,--('2023'!$E$1:$E$997=Streaming!$A4)/COUNTIF('2023'!$E$1:$E$997,Streaming!$A4)) -> 6.63 | C4: =COUNTIF('2023'!$E$1:$E$997,Streaming!$A4) -> 10
A5: Apple | B5: =SUMPRODUCT('2023'!$F$1:$F$997,--('2023'!$E$1:$E$997=Streaming!$A5)/COUNTIF('2023'!$E$1:$E$997,Streaming!$A5)) -> 6.8333333 | C5: =COUNTIF('2023'!$E$1:$E$997,Streaming!$A5) -> 9
A6: Disney | B6: =SUMPRODUCT('2023'!$F$1:$F$997,--('2023'!$E$1:$E$997=Streaming!$A6)/COUNTIF('2023'!$E$1:$E$997,Streaming!$A6)) -> 6.5466667 | C6: =COUNTIF('2023'!$E$1:$E$997,Streaming!$A6) -> 15
A7: Peacock | B7: =SUMPRODUCT('2023'!$F$1:$F$997,--('2023'!$E$1:$E$997=Streaming!$A7)/COUNTIF('2023'!$E$1:$E$997,Streaming!$A7)) -> 5.475 | C7: =COUNTIF('2023'!$E$1:$E$997,Streaming!$A7) -> 12
A8: Paramount | B8: =SUMPRODUCT('2023'!$F$1:$F$997,--('2023'!$E$1:$E$997=Streaming!$A8)/COUNTIF('2023'!$E$1:$E$997,Streaming!$A8)) -> 5.9423077 | C8: =COUNTIF('2023'!$E$1:$E$997,Streaming!$A8) -> 26
A9: Plex | B9: =SUMPRODUCT('2023'!$F$1:$F$997,--('2023'!$E$1:$E$997=Streaming!$A9)/COUNTIF('2023'!$E$1:$E$997,Streaming!$A9)) -> 5.825 | C9: =COUNTIF('2023'!$E$1:$E$997,Streaming!$A9) -> 12
A10: Prime | B10: =SUMPRODUCT('2023'!$F$1:$F$997,--('2023'!$E$1:$E$997=Streaming!$A10)/COUNTIF('2023'!$E$1:$E$997,Streaming!$A10)) -> 6.1431818 | C10: =COUNTIF('2023'!$E$1:$E$997,Streaming!$A10) -> 44

Sheet Awards
A1: Awards | B1: WINNER | C1: HONORABLE MENTIONS
A2: Favorite | B2: 5 | C2: 3 | D2: 3 | E2: 3 | F2: 3
A3: Least Favorite
A4: Best Actor | B4: 4 | C4: 2 | D4: 2 | E4: 2 | F4: 2
A5: Best Actress | B5: 4 | C5: 2 | D5: 2 | E5: 2 | F5: 2
A6: Strangest Role for a Familiar Actor | B6: 1
A7: Best Kids' Movie | B7: 3 | C7: 1 | D7: 1 | E7: 1 | F7: 1
A8: Funniest | B8: 4 | C8: 2 | D8: 2 | E8: 2 | F8: 2
A9: Saddest | B9: 2
A10: Scariest | B10: 2
A11: Best Original Song | B11: 2 | C11: 1 | D11: 1 | E11: 1 | F11: 1
A12: Best Scene | B12: 3 | C12: 1 | D12: 1 | E12: 1 | F12: 1
A13: Best Animal | B13: 3 | C13: 1 | D13: 1 | E13: 1 | F13: 1
A14: Favorite Character | B14: 3 | C14: 1 | D14: 1 | E14: 1 | F14: 1
A15: Least Favorite Character
A16: Most Unique | B16: 2 | C16: 1 | D16: 1 | E16: 1 | F16: 1
A17: Biggest Twist | B17: 3 | C17: 1 | D17: 1 | E17: 1 | F17: 1
A18: Most Pleasantly Surprised By | B18: 3 | C18: 1 | D18: 1 | E18: 1 | F18: 1
A19: Most Thought I'd Like More
A20: Most Overrated
A21: Most Underrated | B21: 3 | C21: 1 | D21: 1 | E21: 1 | F21: 1
A22: Probably Didn't Get It
A23: Most Want a Sequel | B23: 3 | C23: 1 | D23: 1 | E23: 1 | F23: 1
A24: Most Want to Know More About | B24: 2 | C24: 1 | D24: 1 | E24: 1 | F24: 1
A25: Most Want to Rewatch | B25: 5 | C25: 1 | D25: 1 | E25: 1 | F25: 1
A26: Most Thought We'd See—But Didn't
B27: 1
B28: 1
B29: 1
B30: 1
B31: 1
